Workbook

Sheet 1. customers.csv
A1: customer_id | B1: name | C1: email | D1: phone | E1: city | F1: province | G1: registration_date | H1: gender | I1: age_group
A2: CUST0001 | B2: Andi Rahmawati | C2: andirahmawati229@yahoo.com | D2: 82118196001 | E2: Semarang | F2: Jawa Tengah | G2: 44673 | H2: Male | I2: 25-34
A3: CUST0002 | B3: Sari Sembiring | C3: sarisembiring226@gmail.com | D3: 85794026542 | E3: Semarang | F3: Jawa Tengah | G3: 44886 | H3: Female | I3: 18-24
A4: CUST0003 | B4: Bella Aprilia | C4: bellaaprilia271@gmail.com | D4: 81278161849 | E4: Tangerang | F4: Banten | G4: 45379 | H4: Female | I4: 18-24
A5: CUST0004 | B5: Shinta Hartono | C5: shintahartono82@outlook.com | D5: 82216475255 | E5: Semarang | F5: Jawa Tengah | G5: 45569 | H5: Female | I5: 25-34
A6: CUST0005 | B6: Maulana Hidayat | C6: maulanahidayat651@gmail.com | D6: 82183276483 | E6: Bekasi | F6: Jawa Barat | G6: 44311 | H6: Male | I6: 18-24
A7: CUST0006 | B7: Nadia Iskandar | C7: nadiaiskandar68@outlook.com | D7: 82295376724 | E7: Makassar | F7: Sulawesi Selatan | G7: 44702 | H7: Female | I7: 35-44
A8: CUST0007 | B8: Ratna Sari | C8: ratnasari920@gmail.com | D8: 87865328710 | E8: Medan | F8: Sumatera Utara | G8: 44510 | H8: Female | I8: 25-34
A9: CUST0008 | B9: Yoga Utami | C9: yogautami395@gmail.com | D9: 85697848018 | E9: Denpasar | F9: Bali | G9: 45509 | H9: Male | I9: 25-34
A10: CUST0009 | B10: Rani Simbolon | C10: ranisimbolon977@gmail.com | D10: 89648281489 | E10: Semarang | F10: Jawa Tengah | G10: 44510 | H10: Female | I10: 25-34
A11: CUST0010 | B11: Vera Hutapea | C11: verahutapea614@gmail.com | D11: 85370154303 | E11: Manado | F11: Sulawesi Utara | G11: 44358 | H11: Female | I11: 18-24
A12: CUST0011 | B12: Putri Sembiring | C12: putrisembiring132@yahoo.com | D12: 89578248963 | E12: Balikpapan | F12: Kalimantan Timur | G12: 45609 | H12: Female | I12: 18-24
A13: CUST0012 | B13: Shinta Ramadhan | C13: shintaramadhan922@gmail.com | D13: 85871331509 | E13: Balikpapan | F13: Kalimantan Timur | G13: 44668 | H13: Female | I13: 25-34
... A15: CUST0014 | B15: Hana Halim | C15: hanahalim97@yahoo.com | D15: 81365667010 | E15: Depok | F15: Jawa Barat | G15: 44891 | H15: Female | I15: 35-44
A16: CUST0015 | B16: Sari Permata | C16: saripermata460@gmail.com | E16: Medan | F16: Sumatera Utara | G16: 44300 | H16: Female | I16: 35-44
A17: CUST0016 | B17: Siti Nugroho | C17: sitinugroho171@yahoo.com | D17: 85677360260 | E17: Depok | F17: Jawa Barat | G17: 44740 | H17: Female | I17: 45+
A18: CUST0017 | B18: Wahyu Tanjung | C18: wahyutanjung678@gmail.com | D18: 89672343098 | E18: Surabaya | F18: Jawa Timur | G18: 44839 | H18: Male | I18: 18-24
A19: CUST0018 | B19: Dion Hutapea | C19: dionhutapea59@yahoo.com | D19: 85812191361 | E19: Manado | F19: Sulawesi Utara | G19: 44701 | H19: Male | I19: 25-34
A20: CUST0019 | B20: Rina Halim | C20: rinahalim579@gmail.com | D20: 85854353462 | E20: Malang | F20: Jawa Timur | G20: 45133 | H20: Female | I20: 25-34
A21: CUST0020 | B21: Joko Saputra | C21: jokosaputra637@gmail.com | D21: 87811838425 | E21: Bandung | F21: Jawa Barat | G21: 44697 | H21: Male | I21: 25-34
A22: CUST0021 | B22: Mawar Yulianti | C22: mawaryulianti827@gmail.com | D22: 89580841241 | E22: Medan | F22: Sumatera Utara | G22: 45330 | H22: Female | I22: 18-24
A23: CUST0022 | B23: Fitri Hasanah | C23: fitrihasanah704@yahoo.com | D23: 89548740164 | E23: Surabaya | F23: Jawa Timur | G23: 44204 | H23: Female | I23: 25-34
A24: CUST0023 | B24: Citra Maharani | C24: citramaharani565@gmail.com | D24: 89668011280 | E24: Tangerang | F24: Banten | G24: 45389 | H24: Female | I24: 25-34
A25: CUST0024 | B25: Sri Yulianti | C25: sriyulianti921@outlook.com | D25: 81253315869 | E25: Makassar | F25: Sulawesi Selatan | G25: 44681 | H25: Female | I25: 35-44
A26: CUST0025 | B26: Adi Halim | C26: adihalim184@gmail.com | D26: 89656342160 | E26: Pekanbaru | F26: Riau | G26: 44652 | H26: Male | I26: 18-24
A27: CUST0026 | B27: Nanda Yulianti | C27: nandayulianti229@yahoo.com | D27: 81236541458 | E27: Depok | F27: Jawa Barat | G27: 45588 | H27: Male | I27: 45+
A28: CUST0027 | B28: Dewi Kurniawan | C28: dewikurniawan183@outlook.com | D28: 87840196556 | E28: Pontianak | F28: Kalimantan Barat | G28: 45244 | H28: Female | I28: 18-24
... A80: CUST0079 | B80: Wulan Rahmawati | C80: wulanrahmawati649@gmail.com | D80: 87885698478 | E80: Pontianak | F80: Kalimantan Barat | G80: 45078 | H80: Female | I80: 18-24
A81: CUST0080 | B81: Maulana Tarigan | C81: maulanatarigan441@yahoo.com | E81: Bogor | F81: Jawa Barat | G81: 44837 | H81: Male | I81: 35-44
A82: CUST0081 | B82: Indah Pohan | C82: indahpohan94@gmail.com | D82: 81316152809 | E82: Balikpapan | F82: Kalimantan Timur | G82: 45347 | H82: Female | I82: 25-34
A83: CUST0082 | B83: Bella Tanjung | C83: bellatanjung992@gmail.com | D83: 85294519832 | E83: Pekanbaru | F83: Riau | G83: 44656 | H83: Female | I83: 35-44
A84: CUST0083 | B84: Melati Ramadhan | C84: melatiramadhan781@gmail.com | D84: 85293689980 | E84: Pontianak | F84: Kalimantan Barat | G84: 45544 | H84: Female | I84: 35-44
A85: CUST0084 | B85: Mira Rahmawati | C85: mirarahmawati944@outlook.com | D85: 85350229612 | E85: Jakarta | F85: DKI Jakarta | G85: 44384 | H85: Female | I85: 35-44
A86: CUST0085 | B86: Mega Simbolon | C86: megasimbolon162@outlook.com | D86: 85345991022 | E86: Pontianak | F86: Kalimantan Barat | G86: 44298 | H86: Female | I86: 35-44
A87: CUST0086 | B87: Shinta Tanjung | C87: shintatanjung622@gmail.com | D87: 85764381561 | E87: Malang | F87: Jawa Timur | G87: 45585 | H87: Female | I87: 35-44
A88: CUST0087 | B88: Shinta Yulianti | C88: shintayulianti226@gmail.com | D88: 85690034324 | E88: Malang | F88: Jawa Timur | G88: 44868 | H88: Female | I88: 18-24
A89: CUST0088 | B89: Lia Wardani | C89: liawardani390@yahoo.com | D89: 85838851606 | E89: Jakarta | F89: DKI Jakarta | G89: 45138 | H89: Female | I89: 45+
A90: CUST0089 | B90: Irfan Tanjung | C90: irfantanjung415@gmail.com | D90: 89664160529 | E90: Padang | F90: Sumatera Barat | G90: 45609 | H90: Male | I90: 45+
A91: CUST0090 | B91: Lina Suryadi | C91: linasuryadi604@gmail.com | D91: 85681645352 | E91: Bandung | F91: Jawa Barat | G91: 45242 | H91: Female | I91: 25-34
A92: CUST0091 | B92: Sari Aprilia | C92: sariaprilia745@outlook.com | D92: 89523124329 | E92: Makassar | F92: Sulawesi Selatan | G92: 45539 | H92: Female | I92: 18-24
A93: CUST0092 | B93: Ridho Manurung | C93: ridhomanurung773@gmail.com | D93: 87897995527 | E93: Bandung | F93: Jawa Barat | G93: 45157 | H93: Male | I93: 25-34
... A105: CUST0104 | B105: Maulana Hasanah | C105: maulanahasanah141@yahoo.com | D105: 81247277901 | E105: Jakarta | F105: DKI Jakarta | G105: 44721 | H105: Male | I105: 18-24
A106: CUST0105 | B106: Hasna Utami | C106: hasnautami434@gmail.com | E106: Padang | F106: Sumatera Barat | G106: 44325 | H106: Female | I106: 18-24
A107: CUST0106 | B107: Teguh Sembiring | C107: teguhsembiring648@gmail.com | E107: Palembang | F107: Sumatera Selatan | G107: 45365 | H107: Male | I107: 25-34
A108: CUST0107 | B108: Bambang Hutapea | C108: bambanghutapea70@outlook.com | D108: 85888880670 | E108: Depok | F108: Jawa Barat | G108: 44961 | H108: Male | I108: 25-34
A109: CUST0108 | B109: Putri Aprilia | C109: putriaprilia751@yahoo.com | D109: 89519520585 | E109: Yogyakarta | F109: DI Yogyakarta | G109: 45599 | H109: Female | I109: 25-34
A110: CUST0109 | B110: Ridho Wardani | C110: ridhowardani65@yahoo.com | D110: 89670430305 | E110: Malang | F110: Jawa Timur | G110: 45252 | H110: Male | I110: 25-34
A111: CUST0110 | B111: Putra Hakim | C111: putrahakim772@gmail.com | D111: 89534505415 | E111: Bogor | F111: Jawa Barat | G111: 45016 | H111: Male | I111: 35-44
A112: CUST0111 | B112: Rendi Hasanah | C112: rendihasanah509@yahoo.com | D112: 89675841616 | E112: Pontianak | F112: Kalimantan Barat | G112: 44566 | H112: Male | I112: 25-34
A113: CUST0112 | B113: Rina Putri | C113: rinaputri314@outlook.com | D113: 85796275705 | E113: Pontianak | F113: Kalimantan Barat | G113: 45087 | H113: Female | I113: 25-34
A114: CUST0113 | B114: Agus Hidayat | C114: agushidayat373@gmail.com | D114: 85820297021 | E114: Palembang | F114: Sumatera Selatan | G114: 45518 | H114: Male | I114: 25-34
A115: CUST0114 | B115: Risma Pratama | C115: rismapratama158@gmail.com | D115: 89575571928 | E115: Tangerang | F115: Banten | G115: 45012 | H115: Female | I115: 25-34
A116: CUST0115 | B116: Nia Wijaya | C116: niawijaya512@yahoo.com | D116: 85868144739 | E116: Malang | F116: Jawa Timur | G116: 45618 | H116: Female | I116: 45+
A117: CUST0116 | B117: Nia Lestari | C117: nialestari463@gmail.com | D117: 82171551884 | E117: Malang | F117: Jawa Timur | G117: 44519 | H117: Female | I117: 35-44
A118: CUST0117 | B118: Ridho Wardani | C118: ridhowardani521@outlook.com | D118: 82213237058 | E118: Manado | F118: Sulawesi Utara | G118: 44952 | H118: Male | I118: 25-34
A119: CUST0118 | B119: Fajar Cahyani | C119: fajarcahyani68@gmail.com | D119: 85267866912 | E119: Bekasi | F119: Jawa Barat | G119: 45512 | H119: Male | I119: 18-24
... A130: CUST0129 | B130: Fajar Putri | C130: fajarputri327@gmail.com | D130: 82169495888 | E130: Pekanbaru | F130: Riau | G130: 45648 | H130: Male | I130: 25-34
A131: CUST0130 | B131: Dewi Ramadhan | C131: dewiramadhan690@outlook.com | E131: Manado | F131: Sulawesi Utara | G131: 44663 | H131: Female | I131: 35-44
A132: CUST0131 | B132: Reza Hutapea | C132: rezahutapea794@gmail.com | D132: 85623091307 | E132: Bekasi | F132: Jawa Barat | G132: 45054 | H132: Male | I132: 18-24
A133: CUST0132 | B133: Pandu Siregar | C133: pandusiregar943@gmail.com | D133: 85702838578 | E133: Depok | F133: Jawa Barat | G133: 44839 | H133: Male | I133: 45+
A134: CUST0133 | B134: Mawar Hasanah | C134: mawarhasanah363@gmail.com | D134: 89549733484 | E134: Palembang | F134: Sumatera Selatan | G134: 44806 | H134: Female | I134: 35-44
A135: CUST0134 | B135: Rian Manurung | C135: rianmanurung492@outlook.com | D135: 85384419866 | E135: Tangerang | F135: Banten | G135: 44496 | H135: Male | I135: 25-34
A136: CUST0135 | B136: Fatimah Nugroho | C136: fatimahnugroho947@outlook.com | D136: 85747338484 | E136: Makassar | F136: Sulawesi Selatan | G136: 44420 | H136: Female | I136: 25-34
A137: CUST0136 | B137: Hadi Setiawan | C137: hadisetiawan232@gmail.com | D137: 89530165712 | E137: Jakarta | F137: DKI Jakarta | G137: 45324 | H137: Male | I137: 45+
A138: CUST0137 | B138: Karina Pohan | C138: karinapohan667@gmail.com | D138: 82245401938 | E138: Surabaya | F138: Jawa Timur | G138: 44555 | H138: Female | I138: 25-34
A139: CUST0138 | B139: Eko Iskandar | C139: ekoiskandar191@gmail.com | D139: 89640049915 | E139: Malang | F139: Jawa Timur | G139: 45127 | H139: Male | I139: 45+
A140: CUST0139 | B140: Zahra Lestari | C140: zahralestari480@gmail.com | D140: 85231527420 | E140: Bekasi | F140: Jawa Barat | G140: 44801 | H140: Female | I140: 25-34
A141: CUST0140 | B141: Adi Cahyani | C141: adicahyani847@gmail.com | D141: 85685161227 | E141: Bekasi | F141: Jawa Barat | G141: 44705 | H141: Male | I141: 18-24
A142: CUST0141 | B142: Selvi Rahmawati | C142: selvirahmawati310@outlook.com | D142: 87890453017 | E142: Malang | F142: Jawa Timur | G142: 44524 | H142: Female | I142: 25-34
A143: CUST0142 | B143: Fatimah Yulianti | C143: fatimahyulianti655@gmail.com | D143: 85259332727 | E143: Pontianak | F143: Kalimantan Barat | G143: 44962 | H143: Female | I143: 25-34
... A157: CUST0156 | B157: Putra Putri | C157: putraputri380@yahoo.com | D157: 85360932048 | E157: Manado | F157: Sulawesi Utara | G157: 45383 | H157: Male | I157: 35-44
A158: CUST0157 | B158: Sari Hasanah | C158: sarihasanah389@yahoo.com | E158: Yogyakarta | F158: DI Yogyakarta | G158: 44918 | H158: Female | I158: 18-24
A159: CUST0158 | B159: Indra Wardani | C159: indrawardani658@gmail.com | D159: 81280100623 | E159: Bandung | F159: Jawa Barat | G159: 45645 | H159: Male | I159: 18-24
A160: CUST0159 | B160: Vivi Ramadhan | C160: viviramadhan633@gmail.com | D160: 89597700886 | E160: Jakarta | F160: DKI Jakarta | G160: 44231 | H160: Female | I160: 25-34
A161: CUST0160 | B161: Yuli Wijaya | C161: yuliwijaya833@gmail.com | D161: 89662118233 | E161: Pontianak | F161: Kalimantan Barat | G161: 45275 | H161: Female | I161: 25-34
A162: CUST0161 | B162: Cinta Nugroho | C162: cintanugroho983@outlook.com | D162: 85679334101 | E162: Depok | F162: Jawa Barat | G162: 44973 | H162: Female | I162: 25-34
A163: CUST0162 | B163: Vania Saputra | C163: vaniasaputra85@yahoo.com | D163: 85765918033 | E163: Manado | F163: Sulawesi Utara | G163: 45170 | H163: Female | I163: 25-34
A164: CUST0163 | B164: Bintang Rahmawati | C164: bintangrahmawati578@gmail.com | D164: 89502503926 | E164: Bandung | F164: Jawa Barat | G164: 44809 | H164: Male | I164: 18-24
A165: CUST0164 | B165: Anggun Sembiring | C165: anggunsembiring394@outlook.com | D165: 89621850163 | E165: Bandung | F165: Jawa Barat | G165: 44894 | H165: Female | I165: 25-34
A166: CUST0165 | B166: Teguh Iskandar | C166: teguhiskandar31@outlook.com | D166: 89547735866 | E166: Yogyakarta | F166: DI Yogyakarta | G166: 45589 | H166: Male | I166: 25-34
A167: CUST0166 | B167: Vera Cahyani | C167: veracahyani818@outlook.com | D167: 82211426265 | E167: Tangerang | F167: Banten | G167: 44415 | H167: Female | I167: 18-24
A168: CUST0167 | B168: Rio Ramadhan | C168: rioramadhan105@outlook.com | D168: 82112678886 | E168: Medan | F168: Sumatera Utara | G168: 44250 | H168: Male | I168: 18-24
A169: CUST0168 | B169: Teguh Utami | C169: teguhutami885@outlook.com | D169: 85604661839 | E169: Banjarmasin | F169: Kalimantan Selatan | G169: 44544 | H169: Male | I169: 35-44
A170: CUST0169 | B170: Tika Yulianti | C170: tikayulianti505@outlook.com | D170: 82112646471 | E170: Tangerang | F170: Banten | G170: 44712 | H170: Female | I170: 45+
... A183: CUST0182 | B183: Irfan Saputri | C183: irfansaputri191@gmail.com | D183: 85782827422 | E183: Bekasi | F183: Jawa Barat | G183: 45120 | H183: Male | I183: 25-34
A184: CUST0183 | B184: Budi Manurung | C184: budimanurung200@yahoo.com | E184: Yogyakarta | F184: DI Yogyakarta | G184: 44366 | H184: Male | I184: 25-34
A185: CUST0184 | B185: Doni Fauzi | C185: donifauzi282@gmail.com | D185: 82284279788 | E185: Medan | F185: Sumatera Utara | G185: 45369 | H185: Male | I185: 18-24
A186: CUST0185 | B186: Faisal Sembiring | C186: faisalsembiring779@gmail.com | D186: 89678361340 | E186: Padang | F186: Sumatera Barat | G186: 44735 | H186: Male | I186: 25-34
A187: CUST0186 | B187: Rio Kurniawan | C187: riokurniawan215@yahoo.com | D187: 89695962923 | E187: Semarang | F187: Jawa Tengah | G187: 44318 | H187: Male | I187: 25-34
A188: CUST0187 | B188: Olivia Sembiring | C188: oliviasembiring332@yahoo.com | D188: 89644948126 | E188: Surabaya | F188: Jawa Timur | G188: 44764 | H188: Female | I188: 35-44
A189: CUST0188 | B189: Wulan Suryadi | C189: wulansuryadi729@yahoo.com | D189: 85336729466 | E189: Padang | F189: Sumatera Barat | G189: 44351 | H189: Female | I189: 25-34
A190: CUST0189 | B190: Bambang Iskandar | C190: bambangiskandar768@gmail.com | D190: 85257759017 | E190: Tangerang | F190: Banten | G190: 44326 | H190: Male | I190: 35-44
A191: CUST0190 | B191: Lia Susanti | C191: liasusanti275@gmail.com | D191: 85345892975 | E191: Surabaya | F191: Jawa Timur | G191: 44291 | H191: Female | I191: 18-24
A192: CUST0191 | B192: Anton Wijaya | C192: antonwijaya952@gmail.com | D192: 82177063242 | E192: Denpasar | F192: Bali | G192: 44388 | H192: Male | I192: 35-44
A193: CUST0192 | B193: Kirana Maharani | C193: kiranamaharani406@gmail.com | D193: 89543611037 | E193: Bandung | F193: Jawa Barat | G193: 44468 | H193: Female | I193: 25-34
A194: CUST0193 | B194: Selvi Saputra | C194: selvisaputra713@gmail.com | D194: 85316271361 | E194: Medan | F194: Sumatera Utara | G194: 44408 | H194: Female | I194: 25-34
A195: CUST0194 | B195: Fajar Saputri | C195: fajarsaputri657@yahoo.com | D195: 89521890927 | E195: Tangerang | F195: Banten | G195: 44633 | H195: Male | I195: 25-34
A196: CUST0195 | B196: Mega Cahyani | C196: megacahyani881@gmail.com | D196: 82211219656 | E196: Bekasi | F196: Jawa Barat | G196: 44483 | H196: Female | I196: 18-24
... A198: CUST0197 | B198: Anggi Manurung | C198: anggimanurung116@gmail.com | D198: 82279180552 | E198: Depok | F198: Jawa Barat | G198: 45361 | H198: Female | I198: 25-34
A199: CUST0198 | B199: Mira Pohan | C199: mirapohan18@gmail.com | E199: Malang | F199: Jawa Timur | G199: 45484 | H199: Female | I199: 35-44
...

Sheet 1. customers_clean.csv
A1: customer_id | B1: name | C1: email | D1: phone | E1: city | F1: province | G1: registration_date | H1: gender | I1: age_group
A2: CUST0001 | B2: Andi Rahmawati | C2: andirahmawati229@yahoo.com | D2: 82118196001 | E2: Semarang | F2: Jawa Tengah | G2: 44673 | H2: Male | I2: 25-34
A3: CUST0002 | B3: Sari Sembiring | C3: sarisembiring226@gmail.com | D3: 85794026542 | E3: Semarang | F3: Jawa Tengah | G3: 44886 | H3: Female | I3: 18-24
A4: CUST0003 | B4: Bella Aprilia | C4: bellaaprilia271@gmail.com | D4: 81278161849 | E4: Tangerang | F4: Banten | G4: 45379 | H4: Female | I4: 18-24
A5: CUST0004 | B5: Shinta Hartono | C5: shintahartono82@outlook.com | D5: 82216475255 | E5: Semarang | F5: Jawa Tengah | G5: 45569 | H5: Female | I5: 25-34
A6: CUST0005 | B6: Maulana Hidayat | C6: maulanahidayat651@gmail.com | D6: 82183276483 | E6: Bekasi | F6: Jawa Barat | G6: 44311 | H6: Male | I6: 18-24
A7: CUST0006 | B7: Nadia Iskandar | C7: nadiaiskandar68@outlook.com | D7: 82295376724 | E7: Makassar | F7: Sulawesi Selatan | G7: 44702 | H7: Female | I7: 35-44
A8: CUST0007 | B8: Ratna Sari | C8: ratnasari920@gmail.com | D8: 87865328710 | E8: Medan | F8: Sumatera Utara | G8: 44510 | H8: Female | I8: 25-34
A9: CUST0008 | B9: Yoga Utami | C9: yogautami395@gmail.com | D9: 85697848018 | E9: Denpasar | F9: Bali | G9: 45509 | H9: Male | I9: 25-34
A10: CUST0009 | B10: Rani Simbolon | C10: ranisimbolon977@gmail.com | D10: 89648281489 | E10: Semarang | F10: Jawa Tengah | G10: 44510 | H10: Female | I10: 25-34
A11: CUST0010 | B11: Vera Hutapea | C11: verahutapea614@gmail.com | D11: 85370154303 | E11: Manado | F11: Sulawesi Utara | G11: 44358 | H11: Female | I11: 18-24
A12: CUST0011 | B12: Putri Sembiring | C12: putrisembiring132@yahoo.com | D12: 89578248963 | E12: Balikpapan | F12: Kalimantan Timur | G12: 45609 | H12: Female | I12: 18-24
A13: CUST0012 | B13: Shinta Ramadhan | C13: shintaramadhan922@gmail.com | D13: 85871331509 | E13: Balikpapan | F13: Kalimantan Timur | G13: 44668 | H13: Female | I13: 25-34
... A15: CUST0014 | B15: Hana Halim | C15: hanahalim97@yahoo.com | D15: 81365667010 | E15: Depok | F15: Jawa Barat | G15: 44891 | H15: Female | I15: 35-44
A16: CUST0015 | B16: Sari Permata | C16: saripermata460@gmail.com | D16: Tidak Ada | E16: Medan | F16: Sumatera Utara | G16: 44300 | H16: Female | I16: 35-44
A17: CUST0016 | B17: Siti Nugroho | C17: sitinugroho171@yahoo.com | D17: 85677360260 | E17: Depok | F17: Jawa Barat | G17: 44740 | H17: Female | I17: 45+
A18: CUST0017 | B18: Wahyu Tanjung | C18: wahyutanjung678@gmail.com | D18: 89672343098 | E18: Surabaya | F18: Jawa Timur | G18: 44839 | H18: Male | I18: 18-24
A19: CUST0018 | B19: Dion Hutapea | C19: dionhutapea59@yahoo.com | D19: 85812191361 | E19: Manado | F19: Sulawesi Utara | G19: 44701 | H19: Male | I19: 25-34
A20: CUST0019 | B20: Rina Halim | C20: rinahalim579@gmail.com | D20: 85854353462 | E20: Malang | F20: Jawa Timur | G20: 45133 | H20: Female | I20: 25-34
A21: CUST0020 | B21: Joko Saputra | C21: jokosaputra637@gmail.com | D21: 87811838425 | E21: Bandung | F21: Jawa Barat | G21: 44697 | H21: Male | I21: 25-34
A22: CUST0021 | B22: Mawar Yulianti | C22: mawaryulianti827@gmail.com | D22: 89580841241 | E22: Medan | F22: Sumatera Utara | G22: 45330 | H22: Female | I22: 18-24
A23: CUST0022 | B23: Fitri Hasanah | C23: fitrihasanah704@yahoo.com | D23: 89548740164 | E23: Surabaya | F23: Jawa Timur | G23: 44204 | H23: Female | I23: 25-34
A24: CUST0023 | B24: Citra Maharani | C24: citramaharani565@gmail.com | D24: 89668011280 | E24: Tangerang | F24: Banten | G24: 45389 | H24: Female | I24: 25-34
A25: CUST0024 | B25: Sri Yulianti | C25: sriyulianti921@outlook.com | D25: 81253315869 | E25: Makassar | F25: Sulawesi Selatan | G25: 44681 | H25: Female | I25: 35-44
A26: CUST0025 | B26: Adi Halim | C26: adihalim184@gmail.com | D26: 89656342160 | E26: Pekanbaru | F26: Riau | G26: 44652 | H26: Male | I26: 18-24
A27: CUST0026 | B27: Nanda Yulianti | C27: nandayulianti229@yahoo.com | D27: 81236541458 | E27: Depok | F27: Jawa Barat | G27: 45588 | H27: Male | I27: 45+
A28: CUST0027 | B28: Dewi Kurniawan | C28: dewikurniawan183@outlook.com | D28: 87840196556 | E28: Pontianak | F28: Kalimantan Barat | G28: 45244 | H28: Female | I28: 18-24
... A80: CUST0079 | B80: Wulan Rahmawati | C80: wulanrahmawati649@gmail.com | D80: 87885698478 | E80: Pontianak | F80: Kalimantan Barat | G80: 45078 | H80: Female | I80: 18-24
A81: CUST0080 | B81: Maulana Tarigan | C81: maulanatarigan441@yahoo.com | D81: Tidak Ada | E81: Bogor | F81: Jawa Barat | G81: 44837 | H81: Male | I81: 35-44
A82: CUST0081 | B82: Indah Pohan | C82: indahpohan94@gmail.com | D82: 81316152809 | E82: Balikpapan | F82: Kalimantan Timur | G82: 45347 | H82: Female | I82: 25-34
A83: CUST0082 | B83: Bella Tanjung | C83: bellatanjung992@gmail.com | D83: 85294519832 | E83: Pekanbaru | F83: Riau | G83: 44656 | H83: Female | I83: 35-44
A84: CUST0083 | B84: Melati Ramadhan | C84: melatiramadhan781@gmail.com | D84: 85293689980 | E84: Pontianak | F84: Kalimantan Barat | G84: 45544 | H84: Female | I84: 35-44
A85: CUST0084 | B85: Mira Rahmawati | C85: mirarahmawati944@outlook.com | D85: 85350229612 | E85: Jakarta | F85: DKI Jakarta | G85: 44384 | H85: Female | I85: 35-44
A86: CUST0085 | B86: Mega Simbolon | C86: megasimbolon162@outlook.com | D86: 85345991022 | E86: Pontianak | F86: Kalimantan Barat | G86: 44298 | H86: Female | I86: 35-44
A87: CUST0086 | B87: Shinta Tanjung | C87: shintatanjung622@gmail.com | D87: 85764381561 | E87: Malang | F87: Jawa Timur | G87: 45585 | H87: Female | I87: 35-44
A88: CUST0087 | B88: Shinta Yulianti | C88: shintayulianti226@gmail.com | D88: 85690034324 | E88: Malang | F88: Jawa Timur | G88: 44868 | H88: Female | I88: 18-24
A89: CUST0088 | B89: Lia Wardani | C89: liawardani390@yahoo.com | D89: 85838851606 | E89: Jakarta | F89: DKI Jakarta | G89: 45138 | H89: Female | I89: 45+
A90: CUST0089 | B90: Irfan Tanjung | C90: irfantanjung415@gmail.com | D90: 89664160529 | E90: Padang | F90: Sumatera Barat | G90: 45609 | H90: Male | I90: 45+
A91: CUST0090 | B91: Lina Suryadi | C91: linasuryadi604@gmail.com | D91: 85681645352 | E91: Bandung | F91: Jawa Barat | G91: 45242 | H91: Female | I91: 25-34
A92: CUST0091 | B92: Sari Aprilia | C92: sariaprilia745@outlook.com | D92: 89523124329 | E92: Makassar | F92: Sulawesi Selatan | G92: 45539 | H92: Female | I92: 18-24
A93: CUST0092 | B93: Ridho Manurung | C93: ridhomanurung773@gmail.com | D93: 87897995527 | E93: Bandung | F93: Jawa Barat | G93: 45157 | H93: Male | I93: 25-34
... A105: CUST0104 | B105: Maulana Hasanah | C105: maulanahasanah141@yahoo.com | D105: 81247277901 | E105: Jakarta | F105: DKI Jakarta | G105: 44721 | H105: Male | I105: 18-24
A106: CUST0105 | B106: Hasna Utami | C106: hasnautami434@gmail.com | D106: Tidak Ada | E106: Padang | F106: Sumatera Barat | G106: 44325 | H106: Female | I106: 18-24
A107: CUST0106 | B107: Teguh Sembiring | C107: teguhsembiring648@gmail.com | D107: Tidak Ada | E107: Palembang | F107: Sumatera Selatan | G107: 45365 | H107: Male | I107: 25-34
A108: CUST0107 | B108: Bambang Hutapea | C108: bambanghutapea70@outlook.com | D108: 85888880670 | E108: Depok | F108: Jawa Barat | G108: 44961 | H108: Male | I108: 25-34
A109: CUST0108 | B109: Putri Aprilia | C109: putriaprilia751@yahoo.com | D109: 89519520585 | E109: Yogyakarta | F109: DI Yogyakarta | G109: 45599 | H109: Female | I109: 25-34
A110: CUST0109 | B110: Ridho Wardani | C110: ridhowardani65@yahoo.com | D110: 89670430305 | E110: Malang | F110: Jawa Timur | G110: 45252 | H110: Male | I110: 25-34
A111: CUST0110 | B111: Putra Hakim | C111: putrahakim772@gmail.com | D111: 89534505415 | E111: Bogor | F111: Jawa Barat | G111: 45016 | H111: Male | I111: 35-44
A112: CUST0111 | B112: Rendi Hasanah | C112: rendihasanah509@yahoo.com | D112: 89675841616 | E112: Pontianak | F112: Kalimantan Barat | G112: 44566 | H112: Male | I112: 25-34
A113: CUST0112 | B113: Rina Putri | C113: rinaputri314@outlook.com | D113: 85796275705 | E113: Pontianak | F113: Kalimantan Barat | G113: 45087 | H113: Female | I113: 25-34
A114: CUST0113 | B114: Agus Hidayat | C114: agushidayat373@gmail.com | D114: 85820297021 | E114: Palembang | F114: Sumatera Selatan | G114: 45518 | H114: Male | I114: 25-34
A115: CUST0114 | B115: Risma Pratama | C115: rismapratama158@gmail.com | D115: 89575571928 | E115: Tangerang | F115: Banten | G115: 45012 | H115: Female | I115: 25-34
A116: CUST0115 | B116: Nia Wijaya | C116: niawijaya512@yahoo.com | D116: 85868144739 | E116: Malang | F116: Jawa Timur | G116: 45618 | H116: Female | I116: 45+
A117: CUST0116 | B117: Nia Lestari | C117: nialestari463@gmail.com | D117: 82171551884 | E117: Malang | F117: Jawa Timur | G117: 44519 | H117: Female | I117: 35-44
A118: CUST0117 | B118: Ridho Wardani | C118: ridhowardani521@outlook.com | D118: 82213237058 | E118: Manado | F118: Sulawesi Utara | G118: 44952 | H118: Male | I118: 25-34
A119: CUST0118 | B119: Fajar Cahyani | C119: fajarcahyani68@gmail.com | D119: 85267866912 | E119: Bekasi | F119: Jawa Barat | G119: 45512 | H119: Male | I119: 18-24
... A130: CUST0129 | B130: Fajar Putri | C130: fajarputri327@gmail.com | D130: 82169495888 | E130: Pekanbaru | F130: Riau | G130: 45648 | H130: Male | I130: 25-34
A131: CUST0130 | B131: Dewi Ramadhan | C131: dewiramadhan690@outlook.com | D131: Tidak Ada | E131: Manado | F131: Sulawesi Utara | G131: 44663 | H131: Female | I131: 35-44
A132: CUST0131 | B132: Reza Hutapea | C132: rezahutapea794@gmail.com | D132: 85623091307 | E132: Bekasi | F132: Jawa Barat | G132: 45054 | H132: Male | I132: 18-24
A133: CUST0132 | B133: Pandu Siregar | C133: pandusiregar943@gmail.com | D133: 85702838578 | E133: Depok | F133: Jawa Barat | G133: 44839 | H133: Male | I133: 45+
A134: CUST0133 | B134: Mawar Hasanah | C134: mawarhasanah363@gmail.com | D134: 89549733484 | E134: Palembang | F134: Sumatera Selatan | G134: 44806 | H134: Female | I134: 35-44
A135: CUST0134 | B135: Rian Manurung | C135: rianmanurung492@outlook.com | D135: 85384419866 | E135: Tangerang | F135: Banten | G135: 44496 | H135: Male | I135: 25-34
A136: CUST0135 | B136: Fatimah Nugroho | C136: fatimahnugroho947@outlook.com | D136: 85747338484 | E136: Makassar | F136: Sulawesi Selatan | G136: 44420 | H136: Female | I136: 25-34
A137: CUST0136 | B137: Hadi Setiawan | C137: hadisetiawan232@gmail.com | D137: 89530165712 | E137: Jakarta | F137: DKI Jakarta | G137: 45324 | H137: Male | I137: 45+
A138: CUST0137 | B138: Karina Pohan | C138: karinapohan667@gmail.com | D138: 82245401938 | E138: Surabaya | F138: Jawa Timur | G138: 44555 | H138: Female | I138: 25-34
A139: CUST0138 | B139: Eko Iskandar | C139: ekoiskandar191@gmail.com | D139: 89640049915 | E139: Malang | F139: Jawa Timur | G139: 45127 | H139: Male | I139: 45+
A140: CUST0139 | B140: Zahra Lestari | C140: zahralestari480@gmail.com | D140: 85231527420 | E140: Bekasi | F140: Jawa Barat | G140: 44801 | H140: Female | I140: 25-34
A141: CUST0140 | B141: Adi Cahyani | C141: adicahyani847@gmail.com | D141: 85685161227 | E141: Bekasi | F141: Jawa Barat | G141: 44705 | H141: Male | I141: 18-24
A142: CUST0141 | B142: Selvi Rahmawati | C142: selvirahmawati310@outlook.com | D142: 87890453017 | E142: Malang | F142: Jawa Timur | G142: 44524 | H142: Female | I142: 25-34
A143: CUST0142 | B143: Fatimah Yulianti | C143: fatimahyulianti655@gmail.com | D143: 85259332727 | E143: Pontianak | F143: Kalimantan Barat | G143: 44962 | H143: Female | I143: 25-34
... A157: CUST0156 | B157: Putra Putri | C157: putraputri380@yahoo.com | D157: 85360932048 | E157: Manado | F157: Sulawesi Utara | G157: 45383 | H157: Male | I157: 35-44
A158: CUST0157 | B158: Sari Hasanah | C158: sarihasanah389@yahoo.com | D158: Tidak Ada | E158: Yogyakarta | F158: DI Yogyakarta | G158: 44918 | H158: Female | I158: 18-24
A159: CUST0158 | B159: Indra Wardani | C159: indrawardani658@gmail.com | D159: 81280100623 | E159: Bandung | F159: Jawa Barat | G159: 45645 | H159: Male | I159: 18-24
A160: CUST0159 | B160: Vivi Ramadhan | C160: viviramadhan633@gmail.com | D160: 89597700886 | E160: Jakarta | F160: DKI Jakarta | G160: 44231 | H160: Female | I160: 25-34
A161: CUST0160 | B161: Yuli Wijaya | C161: yuliwijaya833@gmail.com | D161: 89662118233 | E161: Pontianak | F161: Kalimantan Barat | G161: 45275 | H161: Female | I161: 25-34
A162: CUST0161 | B162: Cinta Nugroho | C162: cintanugroho983@outlook.com | D162: 85679334101 | E162: Depok | F162: Jawa Barat | G162: 44973 | H162: Female | I162: 25-34
A163: CUST0162 | B163: Vania Saputra | C163: vaniasaputra85@yahoo.com | D163: 85765918033 | E163: Manado | F163: Sulawesi Utara | G163: 45170 | H163: Female | I163: 25-34
A164: CUST0163 | B164: Bintang Rahmawati | C164: bintangrahmawati578@gmail.com | D164: 89502503926 | E164: Bandung | F164: Jawa Barat | G164: 44809 | H164: Male | I164: 18-24
A165: CUST0164 | B165: Anggun Sembiring | C165: anggunsembiring394@outlook.com | D165: 89621850163 | E165: Bandung | F165: Jawa Barat | G165: 44894 | H165: Female | I165: 25-34
A166: CUST0165 | B166: Teguh Iskandar | C166: teguhiskandar31@outlook.com | D166: 89547735866 | E166: Yogyakarta | F166: DI Yogyakarta | G166: 45589 | H166: Male | I166: 25-34
A167: CUST0166 | B167: Vera Cahyani | C167: veracahyani818@outlook.com | D167: 82211426265 | E167: Tangerang | F167: Banten | G167: 44415 | H167: Female | I167: 18-24
A168: CUST0167 | B168: Rio Ramadhan | C168: rioramadhan105@outlook.com | D168: 82112678886 | E168: Medan | F168: Sumatera Utara | G168: 44250 | H168: Male | I168: 18-24
A169: CUST0168 | B169: Teguh Utami | C169: teguhutami885@outlook.com | D169: 85604661839 | E169: Banjarmasin | F169: Kalimantan Selatan | G169: 44544 | H169: Male | I169: 35-44
A170: CUST0169 | B170: Tika Yulianti | C170: tikayulianti505@outlook.com | D170: 82112646471 | E170: Tangerang | F170: Banten | G170: 44712 | H170: Female | I170: 45+
... A183: CUST0182 | B183: Irfan Saputri | C183: irfansaputri191@gmail.com | D183: 85782827422 | E183: Bekasi | F183: Jawa Barat | G183: 45120 | H183: Male | I183: 25-34
A184: CUST0183 | B184: Budi Manurung | C184: budimanurung200@yahoo.com | D184: Tidak Ada | E184: Yogyakarta | F184: DI Yogyakarta | G184: 44366 | H184: Male | I184: 25-34
A185: CUST0184 | B185: Doni Fauzi | C185: donifauzi282@gmail.com | D185: 82284279788 | E185: Medan | F185: Sumatera Utara | G185: 45369 | H185: Male | I185: 18-24
A186: CUST0185 | B186: Faisal Sembiring | C186: faisalsembiring779@gmail.com | D186: 89678361340 | E186: Padang | F186: Sumatera Barat | G186: 44735 | H186: Male | I186: 25-34
A187: CUST0186 | B187: Rio Kurniawan | C187: riokurniawan215@yahoo.com | D187: 89695962923 | E187: Semarang | F187: Jawa Tengah | G187: 44318 | H187: Male | I187: 25-34
A188: CUST0187 | B188: Olivia Sembiring | C188: oliviasembiring332@yahoo.com | D188: 89644948126 | E188: Surabaya | F188: Jawa Timur | G188: 44764 | H188: Female | I188: 35-44
A189: CUST0188 | B189: Wulan Suryadi | C189: wulansuryadi729@yahoo.com | D189: 85336729466 | E189: Padang | F189: Sumatera Barat | G189: 44351 | H189: Female | I189: 25-34
A190: CUST0189 | B190: Bambang Iskandar | C190: bambangiskandar768@gmail.com | D190: 85257759017 | E190: Tangerang | F190: Banten | G190: 44326 | H190: Male | I190: 35-44
A191: CUST0190 | B191: Lia Susanti | C191: liasusanti275@gmail.com | D191: 85345892975 | E191: Surabaya | F191: Jawa Timur | G191: 44291 | H191: Female | I191: 18-24
A192: CUST0191 | B192: Anton Wijaya | C192: antonwijaya952@gmail.com | D192: 82177063242 | E192: Denpasar | F192: Bali | G192: 44388 | H192: Male | I192: 35-44
A193: CUST0192 | B193: Kirana Maharani | C193: kiranamaharani406@gmail.com | D193: 89543611037 | E193: Bandung | F193: Jawa Barat | G193: 44468 | H193: Female | I193: 25-34
A194: CUST0193 | B194: Selvi Saputra | C194: selvisaputra713@gmail.com | D194: 85316271361 | E194: Medan | F194: Sumatera Utara | G194: 44408 | H194: Female | I194: 25-34
A195: CUST0194 | B195: Fajar Saputri | C195: fajarsaputri657@yahoo.com | D195: 89521890927 | E195: Tangerang | F195: Banten | G195: 44633 | H195: Male | I195: 25-34
A196: CUST0195 | B196: Mega Cahyani | C196: megacahyani881@gmail.com | D196: 82211219656 | E196: Bekasi | F196: Jawa Barat | G196: 44483 | H196: Female | I196: 18-24
... A198: CUST0197 | B198: Anggi Manurung | C198: anggimanurung116@gmail.com | D198: 82279180552 | E198: Depok | F198: Jawa Barat | G198: 45361 | H198: Female | I198: 25-34
A199: CUST0198 | B199: Mira Pohan | C199: mirapohan18@gmail.com | D199: Tidak Ada | E199: Malang | F199: Jawa Timur | G199: 45484 | H199: Female | I199: 35-44
...

Sheet 2. order_items.csv
A1: item_id | B1: order_id | C1: product_id | D1: quantity | E1: unit_price_idr | F1: subtotal_idr
A2: ITM000001 | B2: ORD000001 | C2: PRD070 | D2: 1 | E2: 349000 | F2: 349000
A3: ITM000002 | B3: ORD000001 | C3: PRD001 | D3: 2 | E3: 599000 | F3: 1198000
A4: ITM000003 | B4: ORD000001 | C4: PRD148 | D4: 1 | E4: 449000 | F4: 449000
A5: ITM000004 | B5: ORD000002 | C5: PRD086 | D5: 1 | E5: 329000 | F5: 329000
A6: ITM000005 | B6: ORD000002 | C6: PRD258 | D6: 1 | E6: 129000 | F6: 129000
A7: ITM000006 | B7: ORD000002 | C7: PRD256 | D7: 1 | E7: 49000 | F7: 49000
A8: ITM000007 | B8: ORD000003 | C8: PRD076 | D8: 1 | E8: 199000 | F8: 199000
A9: ITM000008 | B9: ORD000004 | C9: PRD205 | D9: 1 | E9: 119000 | F9: 119000
A10: ITM000009 | B10: ORD000005 | C10: PRD239 | D10: 2 | E10: 179000 | F10: 358000
A11: ITM000010 | B11: ORD000006 | C11: PRD170 | D11: 1 | E11: 349000 | F11: 349000
A12: ITM000011 | B12: ORD000007 | C12: PRD013 | D12: 1 | E12: 149000 | F12: 149000
A13: ITM000012 | B13: ORD000007 | C13: PRD230 | D13: 2 | E13: 129000 | F13: 258000
... A4987: ITM004986 | B4987: ORD003000 | C4987: PRD117 | D4987: 1 | E4987: 49000 | F4987: 49000

Sheet 2. order_items_clean.csv
A1: item_id | B1: order_id | C1: product_id | D1: quantity | E1: unit_price_idr | F1: subtotal_idr
A2: ITM000001 | B2: ORD000001 | C2: PRD070 | D2: 1 | E2: 349000 | F2: 349000
A3: ITM000002 | B3: ORD000001 | C3: PRD001 | D3: 2 | E3: 599000 | F3: 1198000
A4: ITM000003 | B4: ORD000001 | C4: PRD148 | D4: 1 | E4: 449000 | F4: 449000
A5: ITM000004 | B5: ORD000002 | C5: PRD086 | D5: 1 | E5: 329000 | F5: 329000
A6: ITM000005 | B6: ORD000002 | C6: PRD258 | D6: 1 | E6: 129000 | F6: 129000
A7: ITM000006 | B7: ORD000002 | C7: PRD256 | D7: 1 | E7: 49000 | F7: 49000
A8: ITM000007 | B8: ORD000003 | C8: PRD076 | D8: 1 | E8: 199000 | F8: 199000
A9: ITM000008 | B9: ORD000004 | C9: PRD205 | D9: 1 | E9: 119000 | F9: 119000
A10: ITM000009 | B10: ORD000005 | C10: PRD239 | D10: 2 | E10: 179000 | F10: 358000
A11: ITM000010 | B11: ORD000006 | C11: PRD170 | D11: 1 | E11: 349000 | F11: 349000
A12: ITM000011 | B12: ORD000007 | C12: PRD013 | D12: 1 | E12: 149000 | F12: 149000
A13: ITM000012 | B13: ORD000007 | C13: PRD230 | D13: 2 | E13: 129000 | F13: 258000
... A4987: ITM004986 | B4987: ORD003000 | C4987: PRD117 | D4987: 1 | E4987: 49000 | F4987: 49000

Sheet 3. orders.csv
A1: order_id | B1: customer_id | C1: order_date | D1: total_amount_idr | E1: shipping_city | F1: shipping_province | G1: shipping_cost_idr | H1: payment_method | I1: order_status | J1: promo_code | K1: discount_amount_idr | L1: courier
A2: ORD000001 | B2: CUST0474 | C2: 45008 | D2: 1951591 | E2: Banjarmasin | F2: Kalimantan Selatan | G2: 32066 | H2: Transfer Bank | I2: shipped | J2: WEEKEND25 | K2: 44409 | L2: JNE
A3: ORD000002 | B3: CUST0478 | C3: 45714 | D3: 507000 | E3: Palembang | F3: Sumatera Selatan | G3: 33769 | H3: Kartu Kredit | I3: delivered | L3: JNE
A4: ORD000003 | B4: CUST0306 | C4: 44755 | D4: 199000 | E4: Tangerang | F4: Banten | G4: 12060 | H4: Transfer Bank | I4: delivered | L4: SiCepat
A5: ORD000004 | B5: CUST0777 | C5: 45622 | D5: 119000 | E5: Medan | F5: Sumatera Utara | G5: 29005 | H5: Transfer Bank | I5: cancelled | L5: Anteraja
A6: ORD000005 | B6: CUST0210 | C6: 45138 | D6: 358000 | E6: Bandung | F6: Jawa Barat | G6: 11192 | H6: Kartu Kredit | I6: cancelled | L6: JNE
A7: ORD000006 | B7: CUST0444 | C7: 44693 | D7: 349000 | E7: Balikpapan | F7: Kalimantan Timur | G7: 37816 | H7: Transfer Bank | I7: returned | L7: SiCepat
A8: ORD000007 | B8: CUST0170 | C8: 44597 | D8: 407000 | E8: Bekasi | F8: Jawa Barat | G8: 13600 | H8: Transfer Bank | I8: delivered | L8: JNE
A9: ORD000008 | B9: CUST0637 | C9: 45079 | D9: 954364 | E9: Manado | F9: Sulawesi Utara | G9: 34020 | H9: Kartu Kredit | I9: processing | J9: WEEKEND25 | K9: 31636 | L9: J&T
A10: ORD000009 | B10: CUST0677 | C10: 45650 | D10: 230288 | E10: Surabaya | F10: Jawa Timur | G10: 13179 | H10: Transfer Bank | I10: cancelled | J10: HARBOLNAS22 | K10: 18712 | L10: JNE
A11: ORD000010 | B11: CUST0200 | C11: 45030 | D11: 264669 | E11: Pontianak | F11: Kalimantan Barat | G11: 30484 | H11: GoPay | I11: delivered | J11: HARI BELANJA | K11: 14331 | L11: Pos Indonesia
A12: ORD000011 | B12: CUST0225 | C12: 45015 | D12: 226000 | E12: Bekasi | F12: Jawa Barat | G12: 9935 | H12: Transfer Bank | I12: delivered | L12: Anteraja
A13: ORD000012 | B13: CUST0760 | C13: 45241 | D13: 251162 | E13: Balikpapan | F13: Kalimantan Timur | G13: 40940 | H13: OVO | I13: shipped | J13: HARI BELANJA | K13: 27838 | L13: J&T
A14: ORD000013 | B14: CUST0337 | C14: 45704 | D14: 199000 | E14: Depok | F14: Jawa Barat | G14: 9420 | H14: QRIS | I14: delivered | L14: Anteraja
A15: ORD000014 | B15: CUST0225 | C15: 45397 | D15: 334654 | E15: Medan | F15: Sumatera Utara | G15: 36425 | H15: GoPay | I15: delivered | J15: HARI BELANJA | K15: 14346 | L15: SiCepat
A16: ORD000015 | B16: CUST0794 | C16: 44940 | D16: 2537438 | E16: Pekanbaru | F16: Riau | G16: 29080 | H16: Transfer Bank | I16: delivered | J16: NEWUSER | K16: 36562 | L16: JNE
A17: ORD000016 | B17: CUST0441 | C17: 45420 | D17: 1746000 | E17: Manado | F17: Sulawesi Utara | G17: 34701 | H17: GoPay | I17: delivered | L17: J&T
A18: ORD000017 | B18: CUST0715 | C18: 45292 | D18: 355448 | E18: Semarang | F18: Jawa Tengah | G18: 12267 | H18: Transfer Bank | I18: returned | J18: RAMADAN23 | K18: 12552 | L18: J&T
A19: ORD000018 | B19: CUST0597 | C19: 44581 | D19: 119000 | E19: Bogor | F19: Jawa Barat | G19: 11574 | H19: Kartu Kredit | I19: cancelled | L19: SiCepat
A20: ORD000019 | B20: CUST0539 | C20: 44844 | D20: 247331 | E20: Balikpapan | F20: Kalimantan Timur | G20: 37574 | H20: OVO | I20: delivered | J20: FLASHSALE | K20: 20669 | L20: SiCepat
A21: ORD000020 | B21: CUST0712 | C21: 45150 | D21: 377322 | E21: Malang | F21: Jawa Timur | G21: 16405 | H21: OVO | I21: processing | J21: RAMADAN23 | K21: 19678 | L21: J&T
A22: ORD000021 | B22: CUST0111 | C22: 45662 | D22: 748000 | E22: Pontianak | F22: Kalimantan Barat | G22: 32628 | H22: Kartu Kredit | I22: shipped | L22: J&T
A23: ORD000022 | B23: CUST0566 | C23: 45442 | D23: 279000 | E23: Malang | F23: Jawa Timur | G23: 21336 | H23: GoPay | I23: delivered | L23: JNE
A24: ORD000023 | B24: CUST0259 | C24: 45153 | D24: 625000 | E24: Banjarmasin | F24: Kalimantan Selatan | G24: 34512 | H24: Kartu Kredit | I24: cancelled | L24: J&T
A25: ORD000024 | B25: CUST0189 | C25: 44651 | D25: 744000 | E25: Tangerang | F25: Banten | G25: 9763 | H25: GoPay | I25: returned | L25: JNE
A26: ORD000025 | B26: CUST0790 | C26: 44735 | D26: 288000 | E26: Balikpapan | F26: Kalimantan Timur | G26: 40074 | H26: GoPay | I26: delivered | L26: J&T
A27: ORD000026 | B27: CUST0755 | C27: 45429 | D27: 549000 | E27: Tangerang | F27: Banten | G27: 13331 | H27: QRIS | I27: shipped | L27: SiCepat
A28: ORD000027 | B28: CUST0561 | C28: 45140 | D28: 1098000 | E28: Yogyakarta | F28: DI Yogyakarta | G28: 13146 | H28: GoPay | I28: shipped | L28: SiCepat
A29: ORD000028 | B29: CUST0624 | C29: 45470 | D29: 408558 | E29: Balikpapan | F29: Kalimantan Timur | G29: 37360 | H29: Transfer Bank | I29: cancelled | J29: NEWUSER | K29: 39442 | L29: Anteraja
A30: ORD000029 | B30: CUST0245 | C30: 45109 | D30: 298000 | E30: Denpasar | F30: Bali | G30: 28769 | H30: Kartu Kredit | I30: delivered | L30: J&T
A31: ORD000030 | B31: CUST0566 | C31: 44985 | D31: 329000 | E31: Malang | F31: Jawa Timur | G31: 17186 | H31: OVO | I31: delivered | L31: J&T
A32: ORD000031 | B32: CUST0492 | C32: 44650 | D32: 200075 | E32: Pekanbaru | F32: Riau | G32: 26230 | H32: Transfer Bank | I32: delivered | J32: RAMADAN23 | K32: 28925 | L32: JNE
A33: ORD000032 | B33: CUST0317 | C33: 45660 | D33: 624526 | E33: Medan | F33: Sumatera Utara | G33: 38976 | H33: QRIS | I33: returned | J33: HARI BELANJA | K33: 43474 | L33: JNE
A34: ORD000033 | B34: CUST0126 | C34: 45208 | D34: 79000 | E34: Depok | F34: Jawa Barat | G34: 11918 | H34: Kartu Kredit | I34: delivered | L34: J&T
A35: ORD000034 | B35: CUST0636 | C35: 45325 | D35: 279000 | E35: Yogyakarta | F35: DI Yogyakarta | G35: 15802 | H35: Transfer Bank | I35: processing | L35: J&T
A36: ORD000035 | B36: CUST0775 | C36: 45194 | D36: 896000 | E36: Semarang | F36: Jawa Tengah | G36: 13372 | H36: Transfer Bank | I36: shipped | L36: SiCepat
A37: ORD000036 | B37: CUST0571 | C37: 45484 | D37: 548000 | E37: Manado | F37: Sulawesi Utara | G37: 35262 | H37: Kartu Kredit | I37: delivered | L37: JNE
A38: ORD000037 | B38: CUST0323 | C38: 45327 | D38: 218221 | E38: Pontianak | F38: Kalimantan Barat | G38: 36528 | H38: OVO | I38: delivered | J38: HARBOLNAS22 | K38: 30779 | L38: JNE
A39: ORD000038 | B39: CUST0252 | C39: 45117 | D39: 798000 | E39: Balikpapan | F39: Kalimantan Timur | G39: 31746 | H39: Transfer Bank | I39: delivered | L39: Pos Indonesia
A40: ORD000039 | B40: CUST0288 | C40: 45110 | D40: 329000 | E40: Tangerang | F40: Banten | G40: 9615 | H40: GoPay | I40: shipped | L40: J&T
A41: ORD000040 | B41: CUST0141 | C41: 45669 | D41: 570879 | E41: Malang | F41: Jawa Timur | G41: 21984 | H41: Transfer Bank | I41: delivered | J41: HARBOLNAS22 | K41: 28121 | L41: Anteraja
A42: ORD000041 | B42: CUST0319 | C42: 45560 | D42: 428000 | E42: Bandung | F42: Jawa Barat | G42: 10652 | H42: Kartu Kredit | I42: delivered | L42: J&T
A43: ORD000042 | B43: CUST0042 | C43: 45110 | D43: 687278 | E43: Bogor | F43: Jawa Barat | G43: 12204 | H43: OVO | I43: delivered | J43: SALE2024 | K43: 48722 | L43: JNE
A44: ORD000043 | B44: CUST0575 | C44: 45385 | D44: 541268 | E44: Bandung | F44: Jawa Barat | G44: 11516 | H44: OVO | I44: delivered | J44: NEWUSER | K44: 36732 | L44: Anteraja
A45: ORD000044 | B45: CUST0006 | C45: 45431 | D45: 69000 | E45: Makassar | F45: Sulawesi Selatan | G45: 42718 | H45: Kartu Kredit | I45: delivered | L45: JNE
A46: ORD000045 | B46: CUST0353 | C46: 44848 | D46: 152424 | E46: Malang | F46: Jawa Timur | G46: 16206 | H46: Transfer Bank | I46: cancelled | J46: NEWUSER | K46: 26576 | L46: JNE
A47: ORD000046 | B47: CUST0708 | C47: 44647 | D47: 279000 | E47: Medan | F47: Sumatera Utara | G47: 26965 | H47: QRIS | I47: delivered | L47: SiCepat
A48: ORD000047 | B48: CUST0701 | C48: 45025 | D48: 129000 | E48: Manado | F48: Sulawesi Utara | G48: 32046 | H48: OVO | I48: shipped | L48: SiCepat
A49: ORD000048 | B49: CUST0151 | C49: 45350 | D49: 598000 | E49: Bekasi | F49: Jawa Barat | G49: 12367 | H49: GoPay | I49: delivered | L49: JNE
A50: ORD000049 | B50: CUST0679 | C50: 45169 | D50: 108780 | E50: Padang | F50: Sumatera Barat | G50: 24801 | H50: Transfer Bank | I50: delivered | J50: MEMBER10 | K50: 19220 | L50: JNE
A51: ORD000050 | B51: CUST0291 | C51: 45132 | D51: 463402 | E51: Denpasar | F51: Bali | G51: 28676 | H51: Transfer Bank | I51: delivered | J51: HARI BELANJA | K51: 35598 | L51: J&T
A52: ORD000051 | B52: CUST0277 | C52: 45031 | D52: 1040543 | E52: Jakarta | F52: DKI Jakarta | G52: 11199 | H52: Transfer Bank | I52: delivered | J52: MEMBER10 | K52: 36457 | L52: JNE
A53: ORD000052 | B53: CUST0021 | C53: 44600 | D53: 484546 | E53: Denpasar | F53: Bali | G53: 24002 | H53: Kartu Kredit | I53: shipped | J53: HARBOLNAS22 | K53: 31454 | L53: J&T
A54: ORD000053 | B54: CUST0787 | C54: 45549 | D54: 228576 | E54: Tangerang | F54: Banten | G54: 9011 | H54: GoPay | I54: delivered | J54: WEEKEND25 | K54: 49424 | L54: SiCepat
A55: ORD000054 | B55: CUST0579 | C55: 45335 | D55: 179000 | E55: Palembang | F55: Sumatera Selatan | G55: 25215 | H55: Kartu Kredit | I55: delivered | L55: Anteraja
A56: ORD000055 | B56: CUST0442 | C56: 45680 | D56: 499000 | E56: Palembang | F56: Sumatera Selatan | G56: 31259 | H56: Kartu Kredit | I56: delivered | L56: Anteraja
A57: ORD000056 | B57: CUST0106 | C57: 45550 | D57: 225298 | E57: Palembang | F57: Sumatera Selatan | G57: 25616 | H57: OVO | I57: delivered | J57: HARI BELANJA | K57: 23702 | L57: JNE
A58: ORD000057 | B58: CUST0096 | C58: 45036 | D58: 377000 | E58: Pontianak | F58: Kalimantan Barat | G58: 41195 | H58: Transfer Bank | I58: delivered | L58: SiCepat
A59: ORD000058 | B59: CUST0007 | C59: 45715 | D59: 1057000 | E59: Bogor | F59: Jawa Barat | G59: 12709 | H59: Transfer Bank | I59: delivered | L59: JNE
A60: ORD000059 | B60: CUST0570 | C60: 45315 | D60: 208667 | E60: Makassar | F60: Sulawesi Selatan | G60: 40276 | H60: OVO | I60: shipped | J60: SALE2024 | K60: 29333 | L60: JNE
A61: ORD000060 | B61: CUST0472 | C61: 44781 | D61: 298000 | E61: Manado | F61: Sulawesi Utara | G61: 32515 | H61: Transfer Bank | I61: cancelled | L61: JNE
A62: ORD000061 | B62: CUST0486 | C62: 44997 | D62: 870559 | E62: Yogyakarta | F62: DI Yogyakarta | G62: 14434 | H62: OVO | I62: cancelled | J62: SALE2024 | K62: 27441 | L62: JNE
A63: ORD000062 | B63: CUST0731 | C63: 45564 | D63: 428704 | E63: Balikpapan | F63: Kalimantan Timur | G63: 44760 | H63: QRIS | I63: cancelled | J63: HARI BELANJA | K63: 28296 | L63: Anteraja
A64: ORD000063 | B64: CUST0324 | C64: 45046 | D64: 687000 | E64: Balikpapan | F64: Kalimantan Timur | G64: 42645 | H64: Kartu Kredit | I64: delivered | L64: JNE
A65: ORD000064 | B65: CUST0056 | C65: 45278 | D65: 622240 | E65: Medan | F65: Sumatera Utara | G65: 34176 | H65: GoPay | I65: cancelled | J65: SALE2024 | K65: 25760 | L65: J&T
A66: ORD000065 | B66: CUST0052 | C66: 45583 | D66: 129000 | E66: Palembang | F66: Sumatera Selatan | G66: 30831 | H66: OVO | I66: delivered | L66: J&T
A67: ORD000066 | B67: CUST0046 | C67: 45021 | D67: 229000 | E67: Palembang | F67: Sumatera Selatan | G67: 33448 | H67: OVO | I67: delivered | L67: SiCepat
A68: ORD000067 | B68: CUST0472 | C68: 45074 | D68: 387000 | E68: Manado | F68: Sulawesi Utara | G68: 32542 | H68: Kartu Kredit | I68: processing | L68: SiCepat
A69: ORD000068 | B69: CUST0600 | C69: 44902 | D69: 449000 | E69: Pontianak | F69: Kalimantan Barat | G69: 41195 | H69: Transfer Bank | I69: processing | L69: J&T
A70: ORD000069 | B70: CUST0321 | C70: 44983 | D70: 129132 | E70: Malang | F70: Jawa Timur | G70: 20164 | H70: Transfer Bank | I70: delivered | J70: RAMADAN23 | K70: 19868 | L70: J&T
A71: ORD000070 | B71: CUST0180 | C71: 45429 | D71: 122904 | E71: Tangerang | F71: Banten | G71: 9347 | H71: GoPay | I71: delivered | J71: MEMBER10 | K71: 26096 | L71: J&T
A72: ORD000071 | B72: CUST0387 | C72: 45080 | D72: 467921 | E72: Depok | F72: Jawa Barat | G72: 13226 | H72: Transfer Bank | I72: delivered | J72: NEWUSER | K72: 31079 | L72: J&T
A73: ORD000072 | B73: CUST0379 | C73: 45453 | D73: 249000 | E73: Manado | F73: Sulawesi Utara | G73: 38149 | H73: OVO | I73: delivered | L73: JNE
A74: ORD000073 | B74: CUST0629 | C74: 45577 | D74: 660432 | E74: Padang | F74: Sumatera Barat | G74: 24278 | H74: Kartu Kredit | I74: processing | J74: WEEKEND25 | K74: 26568 | L74: Pos Indonesia
A75: ORD000074 | B75: CUST0542 | C75: 44834 | D75: 707000 | E75: Semarang | F75: Jawa Tengah | G75: 12040 | H75: Transfer Bank | I75: shipped | L75: Pos Indonesia
A76: ORD000075 | B76: CUST0388 | C76: 45399 | D76: 258000 | E76: Pontianak | F76: Kalimantan Barat | G76: 34548 | H76: Transfer Bank | I76: delivered | L76: JNE
A77: ORD000076 | B77: CUST0315 | C77: 44986 | D77: 1066000 | E77: Bogor | F77: Jawa Barat | G77: 13438 | H77: Kartu Kredit | I77: delivered | L77: SiCepat
A78: ORD000077 | B78: CUST0400 | C78: 45243 | D78: 319744 | E78: Manado | F78: Sulawesi Utara | G78: 44292 | H78: GoPay | I78: delivered | J78: SALE2024 | K78: 29256 | L78: Anteraja
A79: ORD000078 | B79: CUST0197 | C79: 45679 | D79: 1062859 | E79: Depok | F79: Jawa Barat | G79: 12090 | H79: GoPay | I79: processing | J79: RAMADAN23 | K79: 34141 | L79: Anteraja
A80: ORD000079 | B80: CUST0248 | C80: 45552 | D80: 530836 | E80: Pekanbaru | F80: Riau | G80: 26512 | H80: GoPay | I80: returned | J80: NEWUSER | K80: 24164 | L80: J&T
A81: ORD000080 | B81: CUST0214 | C81: 45695 | D81: 113515 | E81: Denpasar | F81: Bali | G81: 29619 | H81: GoPay | I81: shipped | J81: HARI BELANJA | K81: 44485 | L81: J&T
A82: ORD000081 | B82: CUST0478 | C82: 45340 | D82: 216431 | E82: Palembang | F82: Sumatera Selatan | G82: 25254 | H82: Transfer Bank | I82: delivered | J82: NEWUSER | K82: 12569 | L82: SiCepat
A83: ORD000082 | B83: CUST0417 | C83: 45629 | D83: 597000 | E83: Pontianak | F83: Kalimantan Barat | G83: 40474 | H83: GoPay | I83: processing | L83: J&T
A84: ORD000083 | B84: CUST0798 | C84: 45564 | D84: 258000 | E84: Yogyakarta | F84: DI Yogyakarta | G84: 14514 | H84: Transfer Bank | I84: delivered | L84: SiCepat
A85: ORD000084 | B85: CUST0014 | C85: 45118 | D85: 398000 | E85: Depok | F85: Jawa Barat | G85: 13074 | H85: Transfer Bank | I85: delivered | L85: Pos Indonesia
A86: ORD000085 | B86: CUST0697 | C86: 45097 | D86: 533274 | E86: Bandung | F86: Jawa Barat | G86: 11097 | H86: Kartu Kredit | I86: delivered | J86: WEEKEND25 | K86: 44726 | L86: SiCepat
A87: ORD000086 | B87: CUST0489 | C87: 44945 | D87: 567033 | E87: Depok | F87: Jawa Barat | G87: 12336 | H87: Transfer Bank | I87: processing | J87: MEMBER10 | K87: 31967 | L87: JNE
A88: ORD000087 | B88: CUST0346 | C88: 44966 | D88: 647000 | E88: Malang | F88: Jawa Timur | G88: 15065 | H88: GoPay | I88: delivered | L88: SiCepat
A89: ORD000088 | B89: CUST0762 | C89: 44899 | D89: 757000 | E89: Balikpapan | F89: Kalimantan Timur | G89: 32110 | H89: GoPay | I89: processing | L89: Anteraja
A90: ORD000089 | B90: CUST0782 | C90: 44642 | D90: 657000 | E90: Denpasar | F90: Bali | G90: 25249 | H90: QRIS | I90: delivered | L90: Pos Indonesia
A91: ORD000090 | B91: CUST0188 | C91: 44973 | D91: 639659 | E91: Padang | F91: Sumatera Barat | G91: 31950 | H91: GoPay | I91: delivered | J91: MEMBER10 | K91: 46341 | L91: Anteraja
A92: ORD000091 | B92: CUST0006 | C92: 45529 | D92: 478000 | E92: Makassar | F92: Sulawesi Selatan | G92: 34889 | H92: Transfer Bank | I92: cancelled | L92: Anteraja
A93: ORD000092 | B93: CUST0630 | C93: 45295 | D93: 825967 | E93: Bandung | F93: Jawa Barat | G93: 13698 | H93: OVO | I93: delivered | J93: SALE2024 | K93: 11033 | L93: SiCepat
A94: ORD000093 | B94: CUST0732 | C94: 45707 | D94: 637000 | E94: Depok | F94: Jawa Barat | G94: 13897 | H94: OVO | I94: shipped | L94: SiCepat
A95: ORD000094 | B95: CUST0658 | C95: 45589 | D95: 1327000 | E95: Banjarmasin | F95: Kalimantan Selatan | G95: 39112 | H95: Kartu Kredit | I95: cancelled | L95: JNE
A96: ORD000095 | B96: CUST0583 | C96: 45096 | D96: 207000 | E96: Medan | F96: Sumatera Utara | G96: 25348 | H96: Kartu Kredit | I96: cancelled | L96: J&T
A97: ORD000096 | B97: CUST0229 | C97: 45010 | D97: 328000 | E97: Depok | F97: Jawa Barat | G97: 13619 | H97: OVO | I97: cancelled | L97: J&T
A98: ORD000097 | B98: CUST0428 | C98: 45678 | D98: 499000 | E98: Manado | F98: Sulawesi Utara | G98: 44276 | H98: Transfer Bank | I98: delivered | L98: Pos Indonesia
A99: ORD000098 | B99: CUST0371 | C99: 45540 | D99: 1114630 | E99: Bandung | F99: Jawa Barat | G99: 14596 | H99: Kartu Kredit | I99: processing | J99: WEEKEND25 | K99: 32370 | L99: Pos Indonesia
A100: ORD000099 | B100: CUST0031 | C100: 45364 | D100: 134229 | E100: Pontianak | F100: Kalimantan Barat | G100: 33877 | H100: GoPay | I100: delivered | J100: WEEKEND25 | K100: 14771 | L100: SiCepat
...

Sheet 3. orders_clean.csv
A1: order_id | B1: customer_id | C1: order_date | D1: total_amount_idr | E1: shipping_city | F1: shipping_province | G1: shipping_cost_idr | H1: payment_method | I1: order_status | J1: is_lost_revenue | K1: promo_code | L1: discount_amount_idr | M1: courier
A2: ORD000001 | B2: CUST0474 | C2: 45008 | D2: 1951591 | E2: Banjarmasin | F2: Kalimantan Selatan | G2: 32066 | H2: Transfer Bank | I2: shipped | J2: =IF(OR(I2="cancelled",I2="returned"),TRUE,FALSE) -> FALSE | K2: WEEKEND25 | L2: 44409 | M2: JNE
A3: ORD000002 | B3: CUST0478 | C3: 45714 | D3: 507000 | E3: Palembang | F3: Sumatera Selatan | G3: 33769 | H3: Kartu Kredit | I3: delivered | J3: =IF(OR(I3="cancelled",I3="returned"),TRUE,FALSE) -> FALSE | K3: No Promo | L3: 0 | M3: JNE
A4: ORD000003 | B4: CUST0306 | C4: 44755 | D4: 199000 | E4: Tangerang | F4: Banten | G4: 12060 | H4: Transfer Bank | I4: delivered | J4: =IF(OR(I4="cancelled",I4="returned"),TRUE,FALSE) -> FALSE | K4: No Promo | L4: 0 | M4: SiCepat
A5: ORD000004 | B5: CUST0777 | C5: 45622 | D5: 119000 | E5: Medan | F5: Sumatera Utara | G5: 29005 | H5: Transfer Bank | I5: cancelled | J5: =IF(OR(I5="cancelled",I5="returned"),TRUE,FALSE) -> TRUE | K5: No Promo | L5: 0 | M5: Anteraja
A6: ORD000005 | B6: CUST0210 | C6: 45138 | D6: 358000 | E6: Bandung | F6: Jawa Barat | G6: 11192 | H6: Kartu Kredit | I6: cancelled | J6: =IF(OR(I6="cancelled",I6="returned"),TRUE,FALSE) -> TRUE | K6: No Promo | L6: 0 | M6: JNE
A7: ORD000006 | B7: CUST0444 | C7: 44693 | D7: 349000 | E7: Balikpapan | F7: Kalimantan Timur | G7: 37816 | H7: Transfer Bank | I7: returned | J7: =IF(OR(I7="cancelled",I7="returned"),TRUE,FALSE) -> TRUE | K7: No Promo | L7: 0 | M7: SiCepat
A8: ORD000007 | B8: CUST0170 | C8: 44597 | D8: 407000 | E8: Bekasi | F8: Jawa Barat | G8: 13600 | H8: Transfer Bank | I8: delivered | J8: =IF(OR(I8="cancelled",I8="returned"),TRUE,FALSE) -> FALSE | K8: No Promo | L8: 0 | M8: JNE
A9: ORD000008 | B9: CUST0637 | C9: 45079 | D9: 954364 | E9: Manado | F9: Sulawesi Utara | G9: 34020 | H9: Kartu Kredit | I9: processing | J9: =IF(OR(I9="cancelled",I9="returned"),TRUE,FALSE) -> FALSE | K9: WEEKEND25 | L9: 31636 | M9: J&T
A10: ORD000009 | B10: CUST0677 | C10: 45650 | D10: 230288 | E10: Surabaya | F10: Jawa Timur | G10: 13179 | H10: Transfer Bank | I10: cancelled | J10: =IF(OR(I10="cancelled",I10="returned"),TRUE,FALSE) -> TRUE | K10: HARBOLNAS22 | L10: 18712 | M10: JNE
A11: ORD000010 | B11: CUST0200 | C11: 45030 | D11: 264669 | E11: Pontianak | F11: Kalimantan Barat | G11: 30484 | H11: GoPay | I11: delivered | J11: =IF(OR(I11="cancelled",I11="returned"),TRUE,FALSE) -> FALSE | K11: HARI BELANJA | L11: 14331 | M11: Pos Indonesia
A12: ORD000011 | B12: CUST0225 | C12: 45015 | D12: 226000 | E12: Bekasi | F12: Jawa Barat | G12: 9935 | H12: Transfer Bank | I12: delivered | J12: =IF(OR(I12="cancelled",I12="returned"),TRUE,FALSE) -> FALSE | K12: No Promo | L12: 0 | M12: Anteraja
A13: ORD000012 | B13: CUST0760 | C13: 45241 | D13: 251162 | E13: Balikpapan | F13: Kalimantan Timur | G13: 40940 | H13: OVO | I13: shipped | J13: =IF(OR(I13="cancelled",I13="returned"),TRUE,FALSE) -> FALSE | K13: HARI BELANJA | L13: 27838 | M13: J&T
... A3001: ORD003000 | B3001: CUST0556 | C3001: 45434 | D3001: 38484 | E3001: Depok | F3001: Jawa Barat | G3001: 13709 | H3001: OVO | I3001: returned | J3001: =IF(OR(I3001="cancelled",I3001="returned"),TRUE,FALSE) -> TRUE | K3001: RAMADAN23 | L3001: 10516 | M3001: J&T

Sheet 4. products.csv
A1: product_id | B1: name | C1: category | D1: sub_category | E1: price_idr | F1: stock | G1: brand | H1: material | I1: avg_rating
A2: PRD001 | B2: Dress Bodycon Pesona Indo | C2: dress | D2: Atasan Wanita | E2: 599000 | F2: 0 | G2: Pesona Indo | H2: Linen | I2: 5
A3: PRD002 | B3: Kaos Oversize BajuKita | C3: T-Shirt | D3: Atasan Pria | E3: 329000 | F3: 239 | G3: BajuKita | H3: Cotton 100% | I3: 3.7
A4: PRD003 | B4: Dress Maxi Polos Senja Wear | C4: dress | D4: Atasan Wanita | E4: 349000 | F4: 80 | G4: Senja Wear | H4: Cotton-Polyester | I4: 4.7
A5: PRD004 | B5: Ikat Pinggang Kulit Cendana Co | C5: Accessories | D5: Aksesoris | E5: 199000 | F5: 309 | G5: Cendana Co | H5: Denim | I5: 4.6
A6: PRD005 | B6: Dress Bodycon Senja Wear | C6: dress | D6: Atasan Wanita | E6: 599000 | F6: 192 | G6: Senja Wear | H6: Polyester | I6: 3.5
A7: PRD006 | B7: Celana Kulot Tropika Style | C7: Pants | D7: Bawahan Wanita | E7: 119000 | F7: 193 | G7: Tropika Style | H7: Polyester | I7: 4.9
A8: PRD007 | B8: T-Shirt Graphic Cendana Co | C8: Kaos | D8: Atasan Wanita | E8: 119000 | F8: 1 | G8: Cendana Co | H8: Rayon | I8: 4.9
A9: PRD008 | B9: Jaket Bomber Senja Wear | C9: Jaket | D9: Outwear | E9: 549000 | F9: 222 | G9: Senja Wear | H9: Denim | I9: 3.9
A10: PRD009 | B10: Kaos Striped Riang Apparel | C10: T-Shirt | D10: Atasan Pria | E10: 499000 | F10: 41 | G10: Riang Apparel | H10: Twill | I10: 4.7
A11: PRD010 | B11: Kaos Raglan BajuKita | C11: kaos | D11: Atasan Pria | E11: 99000 | F11: 414 | G11: BajuKita | H11: Cotton Combed 30s | I11: 3.6
A12: PRD011 | B12: Topi Baseball Cendana Co | C12: Aksesoris | D12: Aksesoris | E12: 149000 | F12: 370 | G12: Cendana Co | H12: Rayon | I12: 4.8
A13: PRD012 | B13: Kemeja Batik NusaBrand | C13: Shirt | D13: Atasan Wanita | E13: 599000 | F13: 26 | G13: NusaBrand | H13: Twill | I13: 3.7
... A25: PRD024 | B25: Kemeja Linen Tropika Style | C25: Shirt | D25: Atasan Pria | E25: 149000 | F25: 37 | G25: Tropika Style | H25: Polyester | I25: 4.9
A26: PRD025 | B26: Jacket Denim Kanvas Lokal | C26: Jaket | D26: Outwear | E26: 59000 | F26: 272 | G26: Kanvas Lokal | I26: 4.1
A27: PRD026 | B27: Dress Mini Casual BajuKita | C27: Dress | D27: Atasan Wanita | E27: 179000 | F27: 20 | G27: BajuKita | H27: Linen | I27: 4.2
A28: PRD027 | B28: Dompet Kulit Cendana Co | C28: Aksesoris | D28: Aksesoris | E28: 229000 | F28: 1 | G28: Cendana Co | H28: Katun Bambu | I28: 4.3
A29: PRD028 | B29: Dress Bodycon Tropika Style | C29: Dress | D29: Atasan Wanita | E29: 299000 | F29: 112 | G29: Tropika Style | H29: Rayon | I29: 4.6
A30: PRD029 | B30: Shirt Slim Fit Tropika Style | C30: kemeja | D30: Atasan Wanita | E30: 499000 | F30: 26 | G30: Tropika Style | H30: Drill | I30: 3.5
A31: PRD030 | B31: Jaket Hoodie Kanvas Lokal | C31: Jaket | D31: Outwear | E31: 199000 | F31: 403 | G31: Kanvas Lokal | H31: Linen | I31: 3.7
A32: PRD031 | B32: Shirt Slim Fit Tropika Style | C32: Kemeja | D32: Atasan Pria | E32: 69000 | F32: 148 | G32: Tropika Style | H32: Denim | I32: 4
A33: PRD032 | B33: Ikat Pinggang Kulit Tropika Style | C33: Accessories | D33: Aksesoris | E33: 99000 | F33: 464 | G33: Tropika Style | H33: Katun Bambu | I33: 4.7
A34: PRD033 | B34: Celana Chino BajuKita | C34: Celana | D34: Bawahan Wanita | E34: 199000 | F34: 197 | G34: BajuKita | H34: Katun Bambu | I34: 3.5
A35: PRD034 | B35: Topi Baseball Senja Wear | C35: Accessories | D35: Aksesoris | E35: 279000 | F35: 79 | G35: Senja Wear | H35: Katun Bambu | I35: 4.6
A36: PRD035 | B36: Jacket Denim Tropika Style | C36: Jacket | D36: Outwear | E36: 399000 | F36: 49 | G36: Tropika Style | H36: Rayon | I36: 4.9
A37: PRD036 | B37: Syal Rajut Pesona Indo | C37: Accessories | D37: Aksesoris | E37: 299000 | F37: 28 | G37: Pesona Indo | H37: Cotton Combed 30s | I37: 4.8
A38: PRD037 | B38: Dress A-Line Kanvas Lokal | C38: dress | D38: Atasan Wanita | E38: 149000 | F38: 136 | G38: Kanvas Lokal | H38: Cotton 100% | I38: 4.3
... A68: PRD067 | B68: Jaket Parasut Riang Apparel | C68: Jacket | D68: Outwear | E68: 549000 | F68: 11 | G68: Riang Apparel | H68: Cotton-Polyester | I68: 3.5
A69: PRD068 | B69: T-Shirt Graphic Ratu Mode | C69: kaos | D69: Atasan Pria | E69: 129000 | F69: 121 | G69: Ratu Mode | I69: 4.2
A70: PRD069 | B70: Jacket Coach Ratu Mode | C70: Jaket | D70: Outwear | E70: 229000 | F70: 58 | G70: Ratu Mode | H70: Rayon | I70: 4.3
A71: PRD070 | B71: Celana Cargo Pesona Indo | C71: Celana | D71: Bawahan Pria | E71: 349000 | F71: 112 | G71: Pesona Indo | H71: Polyester | I71: 4.5
A72: PRD071 | B72: Dompet Kulit Riang Apparel | C72: Aksesoris | D72: Aksesoris | E72: 99000 | F72: 3 | G72: Riang Apparel | H72: Linen | I72: 4.6
A73: PRD072 | B73: Kaos Polos Basic Ratu Mode | C73: Kaos | D73: Atasan Wanita | E73: 129000 | F73: 199 | G73: Ratu Mode | H73: Cotton Combed 30s | I73: 4.3
A74: PRD073 | B74: Kaos Oversize Riang Apparel | C74: kaos | D74: Atasan Pria | E74: 79000 | F74: 29 | G74: Riang Apparel | H74: Twill | I74: 4.4
A75: PRD074 | B75: Jaket Varsity NusaBrand | C75: Jacket | D75: Outwear | E75: 449000 | F75: 78 | G75: NusaBrand | H75: Linen | I75: 4.4
A76: PRD075 | B76: Ikat Pinggang Kulit Tropika Style | C76: Accessories | D76: Aksesoris | E76: 499000 | F76: 18 | G76: Tropika Style | H76: Katun Bambu | I76: 4.3
A77: PRD076 | B77: Syal Rajut Ratu Mode | C77: Accessories | D77: Aksesoris | E77: 199000 | F77: 18 | G77: Ratu Mode | H77: Katun Bambu | I77: 3.7
A78: PRD077 | B78: Shirt Slim Fit Cendana Co | C78: kemeja | D78: Atasan Pria | E78: 329000 | F78: 32 | G78: Cendana Co | H78: Cotton-Polyester | I78: 4.5
A79: PRD078 | B79: Kaos Striped Cendana Co | C79: kaos | D79: Atasan Wanita | E79: 99000 | F79: 13 | G79: Cendana Co | H79: Twill | I79: 4
A80: PRD079 | B80: Jacket Coach Senja Wear | C80: Jacket | D80: Outwear | E80: 499000 | F80: 14 | G80: Senja Wear | H80: Linen | I80: 4.6
A81: PRD080 | B81: Shirt Slim Fit Cendana Co | C81: Kemeja | D81: Atasan Pria | E81: 329000 | F81: 42 | G81: Cendana Co | I81: 4.2
A82: PRD081 | B82: Celana Jogger Kanvas Lokal | C82: Pants | D82: Bawahan Pria | E82: 229000 | F82: 48 | G82: Kanvas Lokal | H82: Drill | I82: 4.1
A83: PRD082 | B83: Dress Midi Floral Tropika Style | C83: Dress | D83: Atasan Wanita | E83: 229000 | F83: 85 | G83: Tropika Style | H83: Cotton 100% | I83: 4.7
A84: PRD083 | B84: Shirt Slim Fit Kanvas Lokal | C84: Kemeja | D84: Atasan Wanita | E84: 49000 | F84: 21 | G84: Kanvas Lokal | H84: Twill | I84: 4.6
A85: PRD084 | B85: Shirt Slim Fit SandangIndo | C85: Shirt | D85: Atasan Wanita | E85: 69000 | F85: 91 | G85: SandangIndo | H85: Drill | I85: 4.2
A86: PRD085 | B86: Kaos Striped Riang Apparel | C86: T-Shirt | D86: Atasan Wanita | E86: 129000 | F86: 18 | G86: Riang Apparel | H86: Cotton 100% | I86: 4.5
A87: PRD086 | B87: Celana Jogger SandangIndo | C87: Pants | D87: Bawahan Wanita | E87: 329000 | F87: 366 | G87: SandangIndo | I87: 4.7
A88: PRD087 | B88: Kemeja Batik Ratu Mode | C88: Shirt | D88: Atasan Wanita | E88: 399000 | F88: 6 | G88: Ratu Mode | H88: Twill | I88: 4.6
A89: PRD088 | B89: Celana Jeans Slim SandangIndo | C89: Pants | D89: Bawahan Pria | E89: 199000 | F89: 24 | G89: SandangIndo | H89: Katun Bambu | I89: 3.8
A90: PRD089 | B90: Celana Kulot Senja Wear | C90: Pants | D90: Bawahan Pria | E90: 149000 | F90: 39 | G90: Senja Wear | H90: Cotton-Polyester | I90: 4.1
A91: PRD090 | B91: Dress A-Line Kanvas Lokal | C91: Dress | D91: Atasan Wanita | E91: 49000 | F91: 216 | G91: Kanvas Lokal | H91: Rayon | I91: 4.7
A92: PRD091 | B92: Dress Bodycon SandangIndo | C92: dress | D92: Atasan Wanita | E92: 69000 | F92: 73 | G92: SandangIndo | H92: Twill | I92: 3.7
A93: PRD092 | B93: Jaket Varsity Ratu Mode | C93: Jaket | D93: Outwear | E93: 69000 | F93: 160 | G93: Ratu Mode | H93: Polyester | I93: 4.5
A94: PRD093 | B94: Kaos Lengan Panjang Cendana Co | C94: Kaos | D94: Atasan Wanita | E94: 279000 | F94: 2 | G94: Cendana Co | H94: Drill | I94: 4.7
A95: PRD094 | B95: T-Shirt Graphic Tropika Style | C95: Kaos | D95: Atasan Pria | E95: 89000 | F95: 107 | G95: Tropika Style | H95: Rayon | I95: 4.3
A96: PRD095 | B96: Dompet Kulit Pesona Indo | C96: Aksesoris | D96: Aksesoris | E96: 89000 | F96: 13 | G96: Pesona Indo | H96: Cotton Combed 30s | I96: 3.5
A97: PRD096 | B97: Jaket Varsity Kanvas Lokal | C97: Jaket | D97: Outwear | E97: 69000 | F97: 130 | G97: Kanvas Lokal | H97: Linen | I97: 4
A98: PRD097 | B98: Dress Mini Casual Kanvas Lokal | C98: dress | D98: Atasan Wanita | E98: 49000 | F98: 263 | G98: Kanvas Lokal | H98: Cotton-Polyester | I98: 3.5
A99: PRD098 | B99: Topi Baseball Riang Apparel | C99: Aksesoris | D99: Aksesoris | E99: 299000 | F99: 100 | G99: Riang Apparel | H99: Drill | I99: 4.7
... A124: PRD123 | B124: Dress Mini Casual Riang Apparel | C124: Dress | D124: Atasan Wanita | E124: 89000 | F124: 0 | G124: Riang Apparel | H124: Cotton Combed 30s | I124: 4.3
A125: PRD124 | B125: Jacket Denim Riang Apparel | C125: Jaket | D125: Outwear | E125: 179000 | F125: 8 | G125: Riang Apparel | I125: 4.8
A126: PRD125 | B126: Kaos Polos Basic Riang Apparel | C126: kaos | D126: Atasan Wanita | E126: 279000 | F126: 93 | G126: Riang Apparel | H126: Linen | I126: 4.3
A127: PRD126 | B127: Kaos Oversize Riang Apparel | C127: T-Shirt | D127: Atasan Wanita | E127: 279000 | F127: 253 | G127: Riang Apparel | H127: Denim | I127: 4.8
A128: PRD127 | B128: Dompet Kulit Cendana Co | C128: Accessories | D128: Aksesoris | E128: 199000 | F128: 27 | G128: Cendana Co | H128: Cotton Combed 30s | I128: 4.6
A129: PRD128 | B129: Dress Mini Casual Pesona Indo | C129: Dress | D129: Atasan Wanita | E129: 279000 | F129: 253 | G129: Pesona Indo | H129: Katun Bambu | I129: 4.3
A130: PRD129 | B130: Jaket Bomber Pesona Indo | C130: Jacket | D130: Outwear | E130: 79000 | F130: 38 | G130: Pesona Indo | H130: Linen | I130: 4
A131: PRD130 | B131: Dompet Kulit NusaBrand | C131: Accessories | D131: Aksesoris | E131: 229000 | F131: 162 | G131: NusaBrand | H131: Twill | I131: 3.6
A132: PRD131 | B132: Dress Mini Casual Pesona Indo | C132: dress | D132: Atasan Wanita | E132: 99000 | F132: 2 | G132: Pesona Indo | H132: Cotton-Polyester | I132: 4.7
A133: PRD132 | B133: Ikat Pinggang Kulit Kanvas Lokal | C133: Accessories | D133: Aksesoris | E133: 229000 | F133: 120 | G133: Kanvas Lokal | H133: Rayon | I133: 4.2
A134: PRD133 | B134: Tas Selempang Cendana Co | C134: Accessories | D134: Aksesoris | E134: 399000 | F134: 132 | G134: Cendana Co | H134: Polyester | I134: 4.8
A135: PRD134 | B135: Kaos Raglan Cendana Co | C135: kaos | D135: Atasan Wanita | E135: 129000 | F135: 251 | G135: Cendana Co | H135: Cotton Combed 30s | I135: 4.5
A136: PRD135 | B136: Celana Cargo Ratu Mode | C136: Pants | D136: Bawahan Pria | E136: 149000 | F136: 46 | G136: Ratu Mode | H136: Katun Bambu | I136: 4.8
A137: PRD136 | B137: Kemeja Flanel SandangIndo | C137: Kemeja | D137: Atasan Wanita | E137: 119000 | F137: 129 | G137: SandangIndo | H137: Twill | I137: 3.9
... A143: PRD142 | B143: Celana Jogger Ratu Mode | C143: Pants | D143: Bawahan Wanita | E143: 199000 | F143: 239 | G143: Ratu Mode | H143: Polyester | I143: 4
A144: PRD143 | B144: Topi Baseball Cendana Co | C144: Aksesoris | D144: Aksesoris | E144: 329000 | F144: 253 | G144: Cendana Co | I144: 3.8
A145: PRD144 | B145: Celana Jogger Pesona Indo | C145: Celana | D145: Bawahan Wanita | E145: 59000 | F145: 162 | G145: Pesona Indo | H145: Cotton Combed 30s | I145: 4.9
A146: PRD145 | B146: Kemeja Batik NusaBrand | C146: Kemeja | D146: Atasan Wanita | E146: 229000 | F146: 87 | G146: NusaBrand | H146: Cotton Combed 30s | I146: 4.9
A147: PRD146 | B147: Celana Kulot Pesona Indo | C147: Pants | D147: Bawahan Pria | E147: 329000 | F147: 28 | G147: Pesona Indo | H147: Katun Bambu | I147: 4
A148: PRD147 | B148: Tas Selempang Pesona Indo | C148: Accessories | D148: Aksesoris | E148: 349000 | F148: 476 | G148: Pesona Indo | H148: Drill | I148: 4
A149: PRD148 | B149: Kaos Striped Kanvas Lokal | C149: T-Shirt | D149: Atasan Pria | E149: 449000 | F149: 68 | G149: Kanvas Lokal | H149: Polyester | I149: 4.6
A150: PRD149 | B150: Kemeja Oxford NusaBrand | C150: Shirt | D150: Atasan Pria | E150: 549000 | F150: 32 | G150: NusaBrand | H150: Cotton-Polyester | I150: 4.4
A151: PRD150 | B151: Kacamata Hitam Riang Apparel | C151: Accessories | D151: Aksesoris | E151: 89000 | F151: 22 | G151: Riang Apparel | H151: Polyester | I151: 4.6
A152: PRD151 | B152: Celana Jeans Slim Senja Wear | C152: Pants | D152: Bawahan Pria | E152: 249000 | F152: 379 | G152: Senja Wear | H152: Cotton Combed 30s | I152: 4
A153: PRD152 | B153: Kaos Polos Basic Pesona Indo | C153: T-Shirt | D153: Atasan Wanita | E153: 59000 | F153: 36 | G153: Pesona Indo | H153: Cotton 100% | I153: 4.9
A154: PRD153 | B154: Jaket Hoodie Tropika Style | C154: Jaket | D154: Outwear | E154: 179000 | F154: 195 | G154: Tropika Style | H154: Cotton Combed 30s | I154: 4.9
A155: PRD154 | B155: Kemeja Oxford Cendana Co | C155: Shirt | D155: Atasan Wanita | E155: 119000 | F155: 74 | G155: Cendana Co | H155: Drill | I155: 3.8
A156: PRD155 | B156: Dress Wrap NusaBrand | C156: Dress | D156: Atasan Wanita | E156: 499000 | F156: 261 | G156: NusaBrand | H156: Denim | I156: 4.9
... A189: PRD188 | B189: Celana Jeans Slim Senja Wear | C189: Celana | D189: Bawahan Pria | E189: 69000 | F189: 498 | G189: Senja Wear | H189: Katun Bambu | I189: 4.2
A190: PRD189 | B190: Ikat Pinggang Kulit SandangIndo | C190: Aksesoris | D190: Aksesoris | E190: 399000 | F190: 88 | G190: SandangIndo | I190: 4.9
A191: PRD190 | B191: Dress Bodycon Senja Wear | C191: Dress | D191: Atasan Wanita | E191: 129000 | F191: 8 | G191: Senja Wear | H191: Cotton 100% | I191: 3.7
A192: PRD191 | B192: Dress Wrap BajuKita | C192: dress | D192: Atasan Wanita | E192: 49000 | F192: 142 | G192: BajuKita | H192: Polyester | I192: 4.2
A193: PRD192 | B193: T-Shirt Graphic SandangIndo | C193: kaos | D193: Atasan Wanita | E193: 229000 | F193: 95 | G193: SandangIndo | H193: Cotton-Polyester | I193: 4.9
A194: PRD193 | B194: Kaos Striped Kanvas Lokal | C194: T-Shirt | D194: Atasan Pria | E194: 179000 | F194: 71 | G194: Kanvas Lokal | H194: Katun Bambu | I194: 3.5
A195: PRD194 | B195: Jaket Hoodie Senja Wear | C195: Jacket | D195: Outwear | E195: 119000 | F195: 466 | G195: Senja Wear | H195: Cotton 100% | I195: 4.2
A196: PRD195 | B196: Kemeja Casual Senja Wear | C196: Kemeja | D196: Atasan Pria | E196: 149000 | F196: 0 | G196: Senja Wear | H196: Katun Bambu | I196: 4.5
A197: PRD196 | B197: Pants Wide Leg NusaBrand | C197: Celana | D197: Bawahan Pria | E197: 449000 | F197: 2 | G197: NusaBrand | H197: Katun Bambu | I197: 4.1
A198: PRD197 | B198: Kaos Striped Tropika Style | C198: T-Shirt | D198: Atasan Wanita | E198: 199000 | F198: 181 | G198: Tropika Style | H198: Rayon | I198: 3.7
A199: PRD198 | B199: Celana Cargo Senja Wear | C199: Pants | D199: Bawahan Pria | E199: 149000 | F199: 243 | G199: Senja Wear | H199: Rayon | I199: 4.8
A200: PRD199 | B200: Kaos Polos Basic Ratu Mode | C200: Kaos | D200: Atasan Pria | E200: 69000 | F200: 12 | G200: Ratu Mode | H200: Linen | I200: 4.7
A201: PRD200 | B201: Kaos Striped Kanvas Lokal | C201: Kaos | D201: Atasan Pria | E201: 499000 | F201: 89 | G201: Kanvas Lokal | H201: Katun Bambu | I201: 4.4
...

Sheet 4. products_clean.csv
A1: product_id | B1: name | C1: category | D1: category_clean | E1: sub_category | F1: price_idr | G1: stock | H1: brand | I1: material | J1: avg_rating
A2: PRD001 | B2: Dress Bodycon Pesona Indo | C2: dress | D2: =VLOOKUP(C2, mapping_kategori!A:B, 2, false) -> Dress | E2: Atasan Wanita | F2: 599000 | G2: 0 | H2: Pesona Indo | I2: Linen | J2: 5
A3: PRD002 | B3: Kaos Oversize BajuKita | C3: T-Shirt | D3: =VLOOKUP(C3, mapping_kategori!A:B, 2, false) -> T-Shirt | E3: Atasan Pria | F3: 329000 | G3: 239 | H3: BajuKita | I3: Cotton 100% | J3: 3.7
A4: PRD003 | B4: Dress Maxi Polos Senja Wear | C4: dress | D4: =VLOOKUP(C4, mapping_kategori!A:B, 2, false) -> Dress | E4: Atasan Wanita | F4: 349000 | G4: 80 | H4: Senja Wear | I4: Cotton-Polyester | J4: 4.7
A5: PRD004 | B5: Ikat Pinggang Kulit Cendana Co | C5: Accessories | D5: =VLOOKUP(C5, mapping_kategori!A:B, 2, false) -> Accessories | E5: Aksesoris | F5: 199000 | G5: 309 | H5: Cendana Co | I5: Denim | J5: 4.6
A6: PRD005 | B6: Dress Bodycon Senja Wear | C6: dress | D6: =VLOOKUP(C6, mapping_kategori!A:B, 2, false) -> Dress | E6: Atasan Wanita | F6: 599000 | G6: 192 | H6: Senja Wear | I6: Polyester | J6: 3.5
A7: PRD006 | B7: Celana Kulot Tropika Style | C7: Pants | D7: =VLOOKUP(C7, mapping_kategori!A:B, 2, false) -> Pants | E7: Bawahan Wanita | F7: 119000 | G7: 193 | H7: Tropika Style | I7: Polyester | J7: 4.9
A8: PRD007 | B8: T-Shirt Graphic Cendana Co | C8: Kaos | D8: =VLOOKUP(C8, mapping_kategori!A:B, 2, false) -> T-Shirt | E8: Atasan Wanita | F8: 119000 | G8: 1 | H8: Cendana Co | I8: Rayon | J8: 4.9
A9: PRD008 | B9: Jaket Bomber Senja Wear | C9: Jaket | D9: =VLOOKUP(C9, mapping_kategori!A:B, 2, false) -> Jacket | E9: Outwear | F9: 549000 | G9: 222 | H9: Senja Wear | I9: Denim | J9: 3.9
A10: PRD009 | B10: Kaos Striped Riang Apparel | C10: T-Shirt | D10: =VLOOKUP(C10, mapping_kategori!A:B, 2, false) -> T-Shirt | E10: Atasan Pria | F10: 499000 | G10: 41 | H10: Riang Apparel | I10: Twill | J10: 4.7
A11: PRD010 | B11: Kaos Raglan BajuKita | C11: kaos | D11: =VLOOKUP(C11, mapping_kategori!A:B, 2, false) -> T-Shirt | E11: Atasan Pria | F11: 99000 | G11: 414 | H11: BajuKita | I11: Cotton Combed 30s | J11: 3.6
A12: PRD011 | B12: Topi Baseball Cendana Co | C12: Aksesoris | D12: =VLOOKUP(C12, mapping_kategori!A:B, 2, false) -> Accessories | E12: Aksesoris | F12: 149000 | G12: 370 | H12: Cendana Co | I12: Rayon | J12: 4.8
A13: PRD012 | B13: Kemeja Batik NusaBrand | C13: Shirt | D13: =VLOOKUP(C13, mapping_kategori!A:B, 2, false) -> Shirt | E13: Atasan Wanita | F13: 599000 | G13: 26 | H13: NusaBrand | I13: Twill | J13: 3.7
... A25: PRD024 | B25: Kemeja Linen Tropika Style | C25: Shirt | D25: =VLOOKUP(C25, mapping_kategori!A:B, 2, false) -> Shirt | E25: Atasan Pria | F25: 149000 | G25: 37 | H25: Tropika Style | I25: Polyester | J25: 4.9
A26: PRD025 | B26: Jacket Denim Kanvas Lokal | C26: Jaket | D26: =VLOOKUP(C26, mapping_kategori!A:B, 2, false) -> Jacket | E26: Outwear | F26: 59000 | G26: 272 | H26: Kanvas Lokal | J26: 4.1
A27: PRD026 | B27: Dress Mini Casual BajuKita | C27: Dress | D27: =VLOOKUP(C27, mapping_kategori!A:B, 2, false) -> Dress | E27: Atasan Wanita | F27: 179000 | G27: 20 | H27: BajuKita | I27: Linen | J27: 4.2
A28: PRD027 | B28: Dompet Kulit Cendana Co | C28: Aksesoris | D28: =VLOOKUP(C28, mapping_kategori!A:B, 2, false) -> Accessories | E28: Aksesoris | F28: 229000 | G28: 1 | H28: Cendana Co | I28: Katun Bambu | J28: 4.3
A29: PRD028 | B29: Dress Bodycon Tropika Style | C29: Dress | D29: =VLOOKUP(C29, mapping_kategori!A:B, 2, false) -> Dress | E29: Atasan Wanita | F29: 299000 | G29: 112 | H29: Tropika Style | I29: Rayon | J29: 4.6
A30: PRD029 | B30: Shirt Slim Fit Tropika Style | C30: kemeja | D30: =VLOOKUP(C30, mapping_kategori!A:B, 2, false) -> Shirt | E30: Atasan Wanita | F30: 499000 | G30: 26 | H30: Tropika Style | I30: Drill | J30: 3.5
A31: PRD030 | B31: Jaket Hoodie Kanvas Lokal | C31: Jaket | D31: =VLOOKUP(C31, mapping_kategori!A:B, 2, false) -> Jacket | E31: Outwear | F31: 199000 | G31: 403 | H31: Kanvas Lokal | I31: Linen | J31: 3.7
A32: PRD031 | B32: Shirt Slim Fit Tropika Style | C32: Kemeja | D32: =VLOOKUP(C32, mapping_kategori!A:B, 2, false) -> Shirt | E32: Atasan Pria | F32: 69000 | G32: 148 | H32: Tropika Style | I32: Denim | J32: 4
A33: PRD032 | B33: Ikat Pinggang Kulit Tropika Style | C33: Accessories | D33: =VLOOKUP(C33, mapping_kategori!A:B, 2, false) -> Accessories | E33: Aksesoris | F33: 99000 | G33: 464 | H33: Tropika Style | I33: Katun Bambu | J33: 4.7
A34: PRD033 | B34: Celana Chino BajuKita | C34: Celana | D34: =VLOOKUP(C34, mapping_kategori!A:B, 2, false) -> Pants | E34: Bawahan Wanita | F34: 199000 | G34: 197 | H34: BajuKita | I34: Katun Bambu | J34: 3.5
A35: PRD034 | B35: Topi Baseball Senja Wear | C35: Accessories | D35: =VLOOKUP(C35, mapping_kategori!A:B, 2, false) -> Accessories | E35: Aksesoris | F35: 279000 | G35: 79 | H35: Senja Wear | I35: Katun Bambu | J35: 4.6
A36: PRD035 | B36: Jacket Denim Tropika Style | C36: Jacket | D36: =VLOOKUP(C36, mapping_kategori!A:B, 2, false) -> Jacket | E36: Outwear | F36: 399000 | G36: 49 | H36: Tropika Style | I36: Rayon | J36: 4.9
A37: PRD036 | B37: Syal Rajut Pesona Indo | C37: Accessories | D37: =VLOOKUP(C37, mapping_kategori!A:B, 2, false) -> Accessories | E37: Aksesoris | F37: 299000 | G37: 28 | H37: Pesona Indo | I37: Cotton Combed 30s | J37: 4.8
A38: PRD037 | B38: Dress A-Line Kanvas Lokal | C38: dress | D38: =VLOOKUP(C38, mapping_kategori!A:B, 2, false) -> Dress | E38: Atasan Wanita | F38: 149000 | G38: 136 | H38: Kanvas Lokal | I38: Cotton 100% | J38: 4.3
... A68: PRD067 | B68: Jaket Parasut Riang Apparel | C68: Jacket | D68: =VLOOKUP(C68, mapping_kategori!A:B, 2, false) -> Jacket | E68: Outwear | F68: 549000 | G68: 11 | H68: Riang Apparel | I68: Cotton-Polyester | J68: 3.5
A69: PRD068 | B69: T-Shirt Graphic Ratu Mode | C69: kaos | D69: =VLOOKUP(C69, mapping_kategori!A:B, 2, false) -> T-Shirt | E69: Atasan Pria | F69: 129000 | G69: 121 | H69: Ratu Mode | J69: 4.2
A70: PRD069 | B70: Jacket Coach Ratu Mode | C70: Jaket | D70: =VLOOKUP(C70, mapping_kategori!A:B, 2, false) -> Jacket | E70: Outwear | F70: 229000 | G70: 58 | H70: Ratu Mode | I70: Rayon | J70: 4.3
A71: PRD070 | B71: Celana Cargo Pesona Indo | C71: Celana | D71: =VLOOKUP(C71, mapping_kategori!A:B, 2, false) -> Pants | E71: Bawahan Pria | F71: 349000 | G71: 112 | H71: Pesona Indo | I71: Polyester | J71: 4.5
A72: PRD071 | B72: Dompet Kulit Riang Apparel | C72: Aksesoris | D72: =VLOOKUP(C72, mapping_kategori!A:B, 2, false) -> Accessories | E72: Aksesoris | F72: 99000 | G72: 3 | H72: Riang Apparel | I72: Linen | J72: 4.6
A73: PRD072 | B73: Kaos Polos Basic Ratu Mode | C73: Kaos | D73: =VLOOKUP(C73, mapping_kategori!A:B, 2, false) -> T-Shirt | E73: Atasan Wanita | F73: 129000 | G73: 199 | H73: Ratu Mode | I73: Cotton Combed 30s | J73: 4.3
A74: PRD073 | B74: Kaos Oversize Riang Apparel | C74: kaos | D74: =VLOOKUP(C74, mapping_kategori!A:B, 2, false) -> T-Shirt | E74: Atasan Pria | F74: 79000 | G74: 29 | H74: Riang Apparel | I74: Twill | J74: 4.4
A75: PRD074 | B75: Jaket Varsity NusaBrand | C75: Jacket | D75: =VLOOKUP(C75, mapping_kategori!A:B, 2, false) -> Jacket | E75: Outwear | F75: 449000 | G75: 78 | H75: NusaBrand | I75: Linen | J75: 4.4
A76: PRD075 | B76: Ikat Pinggang Kulit Tropika Style | C76: Accessories | D76: =VLOOKUP(C76, mapping_kategori!A:B, 2, false) -> Accessories | E76: Aksesoris | F76: 499000 | G76: 18 | H76: Tropika Style | I76: Katun Bambu | J76: 4.3
A77: PRD076 | B77: Syal Rajut Ratu Mode | C77: Accessories | D77: =VLOOKUP(C77, mapping_kategori!A:B, 2, false) -> Accessories | E77: Aksesoris | F77: 199000 | G77: 18 | H77: Ratu Mode | I77: Katun Bambu | J77: 3.7
A78: PRD077 | B78: Shirt Slim Fit Cendana Co | C78: kemeja | D78: =VLOOKUP(C78, mapping_kategori!A:B, 2, false) -> Shirt | E78: Atasan Pria | F78: 329000 | G78: 32 | H78: Cendana Co | I78: Cotton-Polyester | J78: 4.5
A79: PRD078 | B79: Kaos Striped Cendana Co | C79: kaos | D79: =VLOOKUP(C79, mapping_kategori!A:B, 2, false) -> T-Shirt | E79: Atasan Wanita | F79: 99000 | G79: 13 | H79: Cendana Co | I79: Twill | J79: 4
A80: PRD079 | B80: Jacket Coach Senja Wear | C80: Jacket | D80: =VLOOKUP(C80, mapping_kategori!A:B, 2, false) -> Jacket | E80: Outwear | F80: 499000 | G80: 14 | H80: Senja Wear | I80: Linen | J80: 4.6
A81: PRD080 | B81: Shirt Slim Fit Cendana Co | C81: Kemeja | D81: =VLOOKUP(C81, mapping_kategori!A:B, 2, false) -> Shirt | E81: Atasan Pria | F81: 329000 | G81: 42 | H81: Cendana Co | J81: 4.2
A82: PRD081 | B82: Celana Jogger Kanvas Lokal | C82: Pants | D82: =VLOOKUP(C82, mapping_kategori!A:B, 2, false) -> Pants | E82: Bawahan Pria | F82: 229000 | G82: 48 | H82: Kanvas Lokal | I82: Drill | J82: 4.1
A83: PRD082 | B83: Dress Midi Floral Tropika Style | C83: Dress | D83: =VLOOKUP(C83, mapping_kategori!A:B, 2, false) -> Dress | E83: Atasan Wanita | F83: 229000 | G83: 85 | H83: Tropika Style | I83: Cotton 100% | J83: 4.7
A84: PRD083 | B84: Shirt Slim Fit Kanvas Lokal | C84: Kemeja | D84: =VLOOKUP(C84, mapping_kategori!A:B, 2, false) -> Shirt | E84: Atasan Wanita | F84: 49000 | G84: 21 | H84: Kanvas Lokal | I84: Twill | J84: 4.6
A85: PRD084 | B85: Shirt Slim Fit SandangIndo | C85: Shirt | D85: =VLOOKUP(C85, mapping_kategori!A:B, 2, false) -> Shirt | E85: Atasan Wanita | F85: 69000 | G85: 91 | H85: SandangIndo | I85: Drill | J85: 4.2
A86: PRD085 | B86: Kaos Striped Riang Apparel | C86: T-Shirt | D86: =VLOOKUP(C86, mapping_kategori!A:B, 2, false) -> T-Shirt | E86: Atasan Wanita | F86: 129000 | G86: 18 | H86: Riang Apparel | I86: Cotton 100% | J86: 4.5
A87: PRD086 | B87: Celana Jogger SandangIndo | C87: Pants | D87: =VLOOKUP(C87, mapping_kategori!A:B, 2, false) -> Pants | E87: Bawahan Wanita | F87: 329000 | G87: 366 | H87: SandangIndo | J87: 4.7
A88: PRD087 | B88: Kemeja Batik Ratu Mode | C88: Shirt | D88: =VLOOKUP(C88, mapping_kategori!A:B, 2, false) -> Shirt | E88: Atasan Wanita | F88: 399000 | G88: 6 | H88: Ratu Mode | I88: Twill | J88: 4.6
A89: PRD088 | B89: Celana Jeans Slim SandangIndo | C89: Pants | D89: =VLOOKUP(C89, mapping_kategori!A:B, 2, false) -> Pants | E89: Bawahan Pria | F89: 199000 | G89: 24 | H89: SandangIndo | I89: Katun Bambu | J89: 3.8
A90: PRD089 | B90: Celana Kulot Senja Wear | C90: Pants | D90: =VLOOKUP(C90, mapping_kategori!A:B, 2, false) -> Pants | E90: Bawahan Pria | F90: 149000 | G90: 39 | H90: Senja Wear | I90: Cotton-Polyester | J90: 4.1
A91: PRD090 | B91: Dress A-Line Kanvas Lokal | C91: Dress | D91: =VLOOKUP(C91, mapping_kategori!A:B, 2, false) -> Dress | E91: Atasan Wanita | F91: 49000 | G91: 216 | H91: Kanvas Lokal | I91: Rayon | J91: 4.7
A92: PRD091 | B92: Dress Bodycon SandangIndo | C92: dress | D92: =VLOOKUP(C92, mapping_kategori!A:B, 2, false) -> Dress | E92: Atasan Wanita | F92: 69000 | G92: 73 | H92: SandangIndo | I92: Twill | J92: 3.7
A93: PRD092 | B93: Jaket Varsity Ratu Mode | C93: Jaket | D93: =VLOOKUP(C93, mapping_kategori!A:B, 2, false) -> Jacket | E93: Outwear | F93: 69000 | G93: 160 | H93: Ratu Mode | I93: Polyester | J93: 4.5
A94: PRD093 | B94: Kaos Lengan Panjang Cendana Co | C94: Kaos | D94: =VLOOKUP(C94, mapping_kategori!A:B, 2, false) -> T-Shirt | E94: Atasan Wanita | F94: 279000 | G94: 2 | H94: Cendana Co | I94: Drill | J94: 4.7
A95: PRD094 | B95: T-Shirt Graphic Tropika Style | C95: Kaos | D95: =VLOOKUP(C95, mapping_kategori!A:B, 2, false) -> T-Shirt | E95: Atasan Pria | F95: 89000 | G95: 107 | H95: Tropika Style | I95: Rayon | J95: 4.3
A96: PRD095 | B96: Dompet Kulit Pesona Indo | C96: Aksesoris | D96: =VLOOKUP(C96, mapping_kategori!A:B, 2, false) -> Accessories | E96: Aksesoris | F96: 89000 | G96: 13 | H96: Pesona Indo | I96: Cotton Combed 30s | J96: 3.5
A97: PRD096 | B97: Jaket Varsity Kanvas Lokal | C97: Jaket | D97: =VLOOKUP(C97, mapping_kategori!A:B, 2, false) -> Jacket | E97: Outwear | F97: 69000 | G97: 130 | H97: Kanvas Lokal | I97: Linen | J97: 4
A98: PRD097 | B98: Dress Mini Casual Kanvas Lokal | C98: dress | D98: =VLOOKUP(C98, mapping_kategori!A:B, 2, false) -> Dress | E98: Atasan Wanita | F98: 49000 | G98: 263 | H98: Kanvas Lokal | I98: Cotton-Polyester | J98: 3.5
A99: PRD098 | B99: Topi Baseball Riang Apparel | C99: Aksesoris | D99: =VLOOKUP(C99, mapping_kategori!A:B, 2, false) -> Accessories | E99: Aksesoris | F99: 299000 | G99: 100 | H99: Riang Apparel | I99: Drill | J99: 4.7
... A124: PRD123 | B124: Dress Mini Casual Riang Apparel | C124: Dress | D124: =VLOOKUP(C124, mapping_kategori!A:B, 2, false) -> Dress | E124: Atasan Wanita | F124: 89000 | G124: 0 | H124: Riang Apparel | I124: Cotton Combed 30s | J124: 4.3
A125: PRD124 | B125: Jacket Denim Riang Apparel | C125: Jaket | D125: =VLOOKUP(C125, mapping_kategori!A:B, 2, false) -> Jacket | E125: Outwear | F125: 179000 | G125: 8 | H125: Riang Apparel | J125: 4.8
A126: PRD125 | B126: Kaos Polos Basic Riang Apparel | C126: kaos | D126: =VLOOKUP(C126, mapping_kategori!A:B, 2, false) -> T-Shirt | E126: Atasan Wanita | F126: 279000 | G126: 93 | H126: Riang Apparel | I126: Linen | J126: 4.3
A127: PRD126 | B127: Kaos Oversize Riang Apparel | C127: T-Shirt | D127: =VLOOKUP(C127, mapping_kategori!A:B, 2, false) -> T-Shirt | E127: Atasan Wanita | F127: 279000 | G127: 253 | H127: Riang Apparel | I127: Denim | J127: 4.8
A128: PRD127 | B128: Dompet Kulit Cendana Co | C128: Accessories | D128: =VLOOKUP(C128, mapping_kategori!A:B, 2, false) -> Accessories | E128: Aksesoris | F128: 199000 | G128: 27 | H128: Cendana Co | I128: Cotton Combed 30s | J128: 4.6
A129: PRD128 | B129: Dress Mini Casual Pesona Indo | C129: Dress | D129: =VLOOKUP(C129, mapping_kategori!A:B, 2, false) -> Dress | E129: Atasan Wanita | F129: 279000 | G129: 253 | H129: Pesona Indo | I129: Katun Bambu | J129: 4.3
A130: PRD129 | B130: Jaket Bomber Pesona Indo | C130: Jacket | D130: =VLOOKUP(C130, mapping_kategori!A:B, 2, false) -> Jacket | E130: Outwear | F130: 79000 | G130: 38 | H130: Pesona Indo | I130: Linen | J130: 4
A131: PRD130 | B131: Dompet Kulit NusaBrand | C131: Accessories | D131: =VLOOKUP(C131, mapping_kategori!A:B, 2, false) -> Accessories | E131: Aksesoris | F131: 229000 | G131: 162 | H131: NusaBrand | I131: Twill | J131: 3.6
A132: PRD131 | B132: Dress Mini Casual Pesona Indo | C132: dress | D132: =VLOOKUP(C132, mapping_kategori!A:B, 2, false) -> Dress | E132: Atasan Wanita | F132: 99000 | G132: 2 | H132: Pesona Indo | I132: Cotton-Polyester | J132: 4.7
A133: PRD132 | B133: Ikat Pinggang Kulit Kanvas Lokal | C133: Accessories | D133: =VLOOKUP(C133, mapping_kategori!A:B, 2, false) -> Accessories | E133: Aksesoris | F133: 229000 | G133: 120 | H133: Kanvas Lokal | I133: Rayon | J133: 4.2
A134: PRD133 | B134: Tas Selempang Cendana Co | C134: Accessories | D134: =VLOOKUP(C134, mapping_kategori!A:B, 2, false) -> Accessories | E134: Aksesoris | F134: 399000 | G134: 132 | H134: Cendana Co | I134: Polyester | J134: 4.8
A135: PRD134 | B135: Kaos Raglan Cendana Co | C135: kaos | D135: =VLOOKUP(C135, mapping_kategori!A:B, 2, false) -> T-Shirt | E135: Atasan Wanita | F135: 129000 | G135: 251 | H135: Cendana Co | I135: Cotton Combed 30s | J135: 4.5
A136: PRD135 | B136: Celana Cargo Ratu Mode | C136: Pants | D136: =VLOOKUP(C136, mapping_kategori!A:B, 2, false) -> Pants | E136: Bawahan Pria | F136: 149000 | G136: 46 | H136: Ratu Mode | I136: Katun Bambu | J136: 4.8
A137: PRD136 | B137: Kemeja Flanel SandangIndo | C137: Kemeja | D137: =VLOOKUP(C137, mapping_kategori!A:B, 2, false) -> Shirt | E137: Atasan Wanita | F137: 119000 | G137: 129 | H137: SandangIndo | I137: Twill | J137: 3.9
... A143: PRD142 | B143: Celana Jogger Ratu Mode | C143: Pants | D143: =VLOOKUP(C143, mapping_kategori!A:B, 2, false) -> Pants | E143: Bawahan Wanita | F143: 199000 | G143: 239 | H143: Ratu Mode | I143: Polyester | J143: 4
A144: PRD143 | B144: Topi Baseball Cendana Co | C144: Aksesoris | D144: =VLOOKUP(C144, mapping_kategori!A:B, 2, false) -> Accessories | E144: Aksesoris | F144: 329000 | G144: 253 | H144: Cendana Co | J144: 3.8
A145: PRD144 | B145: Celana Jogger Pesona Indo | C145: Celana | D145: =VLOOKUP(C145, mapping_kategori!A:B, 2, false) -> Pants | E145: Bawahan Wanita | F145: 59000 | G145: 162 | H145: Pesona Indo | I145: Cotton Combed 30s | J145: 4.9
A146: PRD145 | B146: Kemeja Batik NusaBrand | C146: Kemeja | D146: =VLOOKUP(C146, mapping_kategori!A:B, 2, false) -> Shirt | E146: Atasan Wanita | F146: 229000 | G146: 87 | H146: NusaBrand | I146: Cotton Combed 30s | J146: 4.9
A147: PRD146 | B147: Celana Kulot Pesona Indo | C147: Pants | D147: =VLOOKUP(C147, mapping_kategori!A:B, 2, false) -> Pants | E147: Bawahan Pria | F147: 329000 | G147: 28 | H147: Pesona Indo | I147: Katun Bambu | J147: 4
A148: PRD147 | B148: Tas Selempang Pesona Indo | C148: Accessories | D148: =VLOOKUP(C148, mapping_kategori!A:B, 2, false) -> Accessories | E148: Aksesoris | F148: 349000 | G148: 476 | H148: Pesona Indo | I148: Drill | J148: 4
A149: PRD148 | B149: Kaos Striped Kanvas Lokal | C149: T-Shirt | D149: =VLOOKUP(C149, mapping_kategori!A:B, 2, false) -> T-Shirt | E149: Atasan Pria | F149: 449000 | G149: 68 | H149: Kanvas Lokal | I149: Polyester | J149: 4.6
A150: PRD149 | B150: Kemeja Oxford NusaBrand | C150: Shirt | D150: =VLOOKUP(C150, mapping_kategori!A:B, 2, false) -> Shirt | E150: Atasan Pria | F150: 549000 | G150: 32 | H150: NusaBrand | I150: Cotton-Polyester | J150: 4.4
A151: PRD150 | B151: Kacamata Hitam Riang Apparel | C151: Accessories | D151: =VLOOKUP(C151, mapping_kategori!A:B, 2, false) -> Accessories | E151: Aksesoris | F151: 89000 | G151: 22 | H151: Riang Apparel | I151: Polyester | J151: 4.6
A152: PRD151 | B152: Celana Jeans Slim Senja Wear | C152: Pants | D152: =VLOOKUP(C152, mapping_kategori!A:B, 2, false) -> Pants | E152: Bawahan Pria | F152: 249000 | G152: 379 | H152: Senja Wear | I152: Cotton Combed 30s | J152: 4
A153: PRD152 | B153: Kaos Polos Basic Pesona Indo | C153: T-Shirt | D153: =VLOOKUP(C153, mapping_kategori!A:B, 2, false) -> T-Shirt | E153: Atasan Wanita | F153: 59000 | G153: 36 | H153: Pesona Indo | I153: Cotton 100% | J153: 4.9
A154: PRD153 | B154: Jaket Hoodie Tropika Style | C154: Jaket | D154: =VLOOKUP(C154, mapping_kategori!A:B, 2, false) -> Jacket | E154: Outwear | F154: 179000 | G154: 195 | H154: Tropika Style | I154: Cotton Combed 30s | J154: 4.9
A155: PRD154 | B155: Kemeja Oxford Cendana Co | C155: Shirt | D155: =VLOOKUP(C155, mapping_kategori!A:B, 2, false) -> Shirt | E155: Atasan Wanita | F155: 119000 | G155: 74 | H155: Cendana Co | I155: Drill | J155: 3.8
A156: PRD155 | B156: Dress Wrap NusaBrand | C156: Dress | D156: =VLOOKUP(C156, mapping_kategori!A:B, 2, false) -> Dress | E156: Atasan Wanita | F156: 499000 | G156: 261 | H156: NusaBrand | I156: Denim | J156: 4.9
... A189: PRD188 | B189: Celana Jeans Slim Senja Wear | C189: Celana | D189: =VLOOKUP(C189, mapping_kategori!A:B, 2, false) -> Pants | E189: Bawahan Pria | F189: 69000 | G189: 498 | H189: Senja Wear | I189: Katun Bambu | J189: 4.2
A190: PRD189 | B190: Ikat Pinggang Kulit SandangIndo | C190: Aksesoris | D190: =VLOOKUP(C190, mapping_kategori!A:B, 2, false) -> Accessories | E190: Aksesoris | F190: 399000 | G190: 88 | H190: SandangIndo | J190: 4.9
A191: PRD190 | B191: Dress Bodycon Senja Wear | C191: Dress | D191: =VLOOKUP(C191, mapping_kategori!A:B, 2, false) -> Dress | E191: Atasan Wanita | F191: 129000 | G191: 8 | H191: Senja Wear | I191: Cotton 100% | J191: 3.7
A192: PRD191 | B192: Dress Wrap BajuKita | C192: dress | D192: =VLOOKUP(C192, mapping_kategori!A:B, 2, false) -> Dress | E192: Atasan Wanita | F192: 49000 | G192: 142 | H192: BajuKita | I192: Polyester | J192: 4.2
A193: PRD192 | B193: T-Shirt Graphic SandangIndo | C193: kaos | D193: =VLOOKUP(C193, mapping_kategori!A:B, 2, false) -> T-Shirt | E193: Atasan Wanita | F193: 229000 | G193: 95 | H193: SandangIndo | I193: Cotton-Polyester | J193: 4.9
A194: PRD193 | B194: Kaos Striped Kanvas Lokal | C194: T-Shirt | D194: =VLOOKUP(C194, mapping_kategori!A:B, 2, false) -> T-Shirt | E194: Atasan Pria | F194: 179000 | G194: 71 | H194: Kanvas Lokal | I194: Katun Bambu | J194: 3.5
A195: PRD194 | B195: Jaket Hoodie Senja Wear | C195: Jacket | D195: =VLOOKUP(C195, mapping_kategori!A:B, 2, false) -> Jacket | E195: Outwear | F195: 119000 | G195: 466 | H195: Senja Wear | I195: Cotton 100% | J195: 4.2
A196: PRD195 | B196: Kemeja Casual Senja Wear | C196: Kemeja | D196: =VLOOKUP(C196, mapping_kategori!A:B, 2, false) -> Shirt | E196: Atasan Pria | F196: 149000 | G196: 0 | H196: Senja Wear | I196: Katun Bambu | J196: 4.5
A197: PRD196 | B197: Pants Wide Leg NusaBrand | C197: Celana | D197: =VLOOKUP(C197, mapping_kategori!A:B, 2, false) -> Pants | E197: Bawahan Pria | F197: 449000 | G197: 2 | H197: NusaBrand | I197: Katun Bambu | J197: 4.1
A198: PRD197 | B198: Kaos Striped Tropika Style | C198: T-Shirt | D198: =VLOOKUP(C198, mapping_kategori!A:B, 2, false) -> T-Shirt | E198: Atasan Wanita | F198: 199000 | G198: 181 | H198: Tropika Style | I198: Rayon | J198: 3.7
A199: PRD198 | B199: Celana Cargo Senja Wear | C199: Pants | D199: =VLOOKUP(C199, mapping_kategori!A:B, 2, false) -> Pants | E199: Bawahan Pria | F199: 149000 | G199: 243 | H199: Senja Wear | I199: Rayon | J199: 4.8
A200: PRD199 | B200: Kaos Polos Basic Ratu Mode | C200: Kaos | D200: =VLOOKUP(C200, mapping_kategori!A:B, 2, false) -> T-Shirt | E200: Atasan Pria | F200: 69000 | G200: 12 | H200: Ratu Mode | I200: Linen | J200: 4.7
A201: PRD200 | B201: Kaos Striped Kanvas Lokal | C201: Kaos | D201: =VLOOKUP(C201, mapping_kategori!A:B, 2, false) -> T-Shirt | E201: Atasan Pria | F201: 499000 | G201: 89 | H201: Kanvas Lokal | I201: Katun Bambu | J201: 4.4
...

Sheet Data_Master
A1: order_id | B1: product_id | C1: quantity | D1: subtotal_idr | E1: order_date | F1: order_status | G1: is_lost_revenue | H1: shipping_city | I1: shipping_province | J1: category_clean
A2: ORD000001 | B2: PRD070 | C2: 1 | D2: 349000 | E2: {=_xlfn.XLOOKUP(A2, '3. orders_clean.csv'!A:A,'3. orders_clean.csv'!C:C)} -> 45008 | F2: {=_xlfn.XLOOKUP(A2, '3. orders_clean.csv'!A:A, '3. orders_clean.csv'!I:I)} -> shipped | G2: {=_xlfn.XLOOKUP(A2, '3. orders_clean.csv'!A:A, '3. orders_clean.csv'!J:J)} -> FALSE | H2: {=_xlfn.XLOOKUP(A2, '3. orders_clean.csv'!A:A, '3. orders_clean.csv'!E:E)} -> Banjarmasin | I2: {=_xlfn.XLOOKUP(A2, '3. orders_clean.csv'!A:A, '3. orders_clean.csv'!F:F)} -> Kalimantan Selatan | J2: {=_xlfn.XLOOKUP(B:B, '4. products_clean.csv'!A:A, '4. products_clean.csv'!D:D)} -> Pants
A3: ORD000001 | B3: PRD001 | C3: 2 | D3: 1198000 | E3: {=_xlfn.XLOOKUP(A3, '3. orders_clean.csv'!A:A,'3. orders_clean.csv'!C:C)} -> 45008 | F3: {=_xlfn.XLOOKUP(A3, '3. orders_clean.csv'!A:A, '3. orders_clean.csv'!I:I)} -> shipped | G3: {=_xlfn.XLOOKUP(A3, '3. orders_clean.csv'!A:A, '3. orders_clean.csv'!J:J)} -> FALSE | H3: {=_xlfn.XLOOKUP(A3, '3. orders_clean.csv'!A:A, '3. orders_clean.csv'!E:E)} -> Banjarmasin | I3: {=_xlfn.XLOOKUP(A3, '3. orders_clean.csv'!A:A, '3. orders_clean.csv'!F:F)} -> Kalimantan Selatan | J3: {=_xlfn.XLOOKUP(B:B, '4. products_clean.csv'!A:A, '4. products_clean.csv'!D:D)} -> Dress
A4: ORD000001 | B4: PRD148 | C4: 1 | D4: 449000 | E4: {=_xlfn.XLOOKUP(A4, '3. orders_clean.csv'!A:A,'3. orders_clean.csv'!C:C)} -> 45008 | F4: {=_xlfn.XLOOKUP(A4, '3. orders_clean.csv'!A:A, '3. orders_clean.csv'!I:I)} -> shipped | G4: {=_xlfn.XLOOKUP(A4, '3. orders_clean.csv'!A:A, '3. orders_clean.csv'!J:J)} -> FALSE | H4: {=_xlfn.XLOOKUP(A4, '3. orders_clean.csv'!A:A, '3. orders_clean.csv'!E:E)} -> Banjarmasin | I4: {=_xlfn.XLOOKUP(A4, '3. orders_clean.csv'!A:A, '3. orders_clean.csv'!F:F)} -> Kalimantan Selatan | J4: {=_xlfn.XLOOKUP(B:B, '4. products_clean.csv'!A:A, '4. products_clean.csv'!D:D)} -> T-Shirt
A5: ORD000002 | B5: PRD086 | C5: 1 | D5: 329000 | E5: {=_xlfn.XLOOKUP(A5, '3. orders_clean.csv'!A:A,'3. orders_clean.csv'!C:C)} -> 45714 | F5: {=_xlfn.XLOOKUP(A5, '3. orders_clean.csv'!A:A, '3. orders_clean.csv'!I:I)} -> delivered | G5: {=_xlfn.XLOOKUP(A5, '3. orders_clean.csv'!A:A, '3. orders_clean.csv'!J:J)} -> FALSE | H5: {=_xlfn.XLOOKUP(A5, '3. orders_clean.csv'!A:A, '3. orders_clean.csv'!E:E)} -> Palembang | I5: {=_xlfn.XLOOKUP(A5, '3. orders_clean.csv'!A:A, '3. orders_clean.csv'!F:F)} -> Sumatera Selatan | J5: {=_xlfn.XLOOKUP(B:B, '4. products_clean.csv'!A:A, '4. products_clean.csv'!D:D)} -> Pants
A6: ORD000002 | B6: PRD258 | C6: 1 | D6: 129000 | E6: {=_xlfn.XLOOKUP(A6, '3. orders_clean.csv'!A:A,'3. orders_clean.csv'!C:C)} -> 45714 | F6: {=_xlfn.XLOOKUP(A6, '3. orders_clean.csv'!A:A, '3. orders_clean.csv'!I:I)} -> delivered | G6: {=_xlfn.XLOOKUP(A6, '3. orders_clean.csv'!A:A, '3. orders_clean.csv'!J:J)} -> FALSE | H6: {=_xlfn.XLOOKUP(A6, '3. orders_clean.csv'!A:A, '3. orders_clean.csv'!E:E)} -> Palembang | I6: {=_xlfn.XLOOKUP(A6, '3. orders_clean.csv'!A:A, '3. orders_clean.csv'!F:F)} -> Sumatera Selatan | J6: {=_xlfn.XLOOKUP(B:B, '4. products_clean.csv'!A:A, '4. products_clean.csv'!D:D)} -> Accessories
A7: ORD000002 | B7: PRD256 | C7: 1 | D7: 49000 | E7: {=_xlfn.XLOOKUP(A7, '3. orders_clean.csv'!A:A,'3. orders_clean.csv'!C:C)} -> 45714 | F7: {=_xlfn.XLOOKUP(A7, '3. orders_clean.csv'!A:A, '3. orders_clean.csv'!I:I)} -> delivered | G7: {=_xlfn.XLOOKUP(A7, '3. orders_clean.csv'!A:A, '3. orders_clean.csv'!J:J)} -> FALSE | H7: {=_xlfn.XLOOKUP(A7, '3. orders_clean.csv'!A:A, '3. orders_clean.csv'!E:E)} -> Palembang | I7: {=_xlfn.XLOOKUP(A7, '3. orders_clean.csv'!A:A, '3. orders_clean.csv'!F:F)} -> Sumatera Selatan | J7: {=_xlfn.XLOOKUP(B:B, '4. products_clean.csv'!A:A, '4. products_clean.csv'!D:D)} -> Dress
A8: ORD000003 | B8: PRD076 | C8: 1 | D8: 199000 | E8: {=_xlfn.XLOOKUP(A8, '3. orders_clean.csv'!A:A,'3. orders_clean.csv'!C:C)} -> 44755 | F8: {=_xlfn.XLOOKUP(A8, '3. orders_clean.csv'!A:A, '3. orders_clean.csv'!I:I)} -> delivered | G8: {=_xlfn.XLOOKUP(A8, '3. orders_clean.csv'!A:A, '3. orders_clean.csv'!J:J)} -> FALSE | H8: {=_xlfn.XLOOKUP(A8, '3. orders_clean.csv'!A:A, '3. orders_clean.csv'!E:E)} -> Tangerang | I8: {=_xlfn.XLOOKUP(A8, '3. orders_clean.csv'!A:A, '3. orders_clean.csv'!F:F)} -> Banten | J8: {=_xlfn.XLOOKUP(B:B, '4. products_clean.csv'!A:A, '4. products_clean.csv'!D:D)} -> Accessories
A9: ORD000004 | B9: PRD205 | C9: 1 | D9: 119000 | E9: {=_xlfn.XLOOKUP(A9, '3. orders_clean.csv'!A:A,'3. orders_clean.csv'!C:C)} -> 45622 | F9: {=_xlfn.XLOOKUP(A9, '3. orders_clean.csv'!A:A, '3. orders_clean.csv'!I:I)} -> cancelled | G9: {=_xlfn.XLOOKUP(A9, '3. orders_clean.csv'!A:A, '3. orders_clean.csv'!J:J)} -> TRUE | H9: {=_xlfn.XLOOKUP(A9, '3. orders_clean.csv'!A:A, '3. orders_clean.csv'!E:E)} -> Medan | I9: {=_xlfn.XLOOKUP(A9, '3. orders_clean.csv'!A:A, '3. orders_clean.csv'!F:F)} -> Sumatera Utara | J9: {=_xlfn.XLOOKUP(B:B, '4. products_clean.csv'!A:A, '4. products_clean.csv'!D:D)} -> Accessories
A10: ORD000005 | B10: PRD239 | C10: 2 | D10: 358000 | E10: {=_xlfn.XLOOKUP(A10, '3. orders_clean.csv'!A:A,'3. orders_clean.csv'!C:C)} -> 45138 | F10: {=_xlfn.XLOOKUP(A10, '3. orders_clean.csv'!A:A, '3. orders_clean.csv'!I:I)} -> cancelled | G10: {=_xlfn.XLOOKUP(A10, '3. orders_clean.csv'!A:A, '3. orders_clean.csv'!J:J)} -> TRUE | H10: {=_xlfn.XLOOKUP(A10, '3. orders_clean.csv'!A:A, '3. orders_clean.csv'!E:E)} -> Bandung | I10: {=_xlfn.XLOOKUP(A10, '3. orders_clean.csv'!A:A, '3. orders_clean.csv'!F:F)} -> Jawa Barat | J10: {=_xlfn.XLOOKUP(B:B, '4. products_clean.csv'!A:A, '4. products_clean.csv'!D:D)} -> Jacket
A11: ORD000006 | B11: PRD170 | C11: 1 | D11: 349000 | E11: {=_xlfn.XLOOKUP(A11, '3. orders_clean.csv'!A:A,'3. orders_clean.csv'!C:C)} -> 44693 | F11: {=_xlfn.XLOOKUP(A11, '3. orders_clean.csv'!A:A, '3. orders_clean.csv'!I:I)} -> returned | G11: {=_xlfn.XLOOKUP(A11, '3. orders_clean.csv'!A:A, '3. orders_clean.csv'!J:J)} -> TRUE | H11: {=_xlfn.XLOOKUP(A11, '3. orders_clean.csv'!A:A, '3. orders_clean.csv'!E:E)} -> Balikpapan | I11: {=_xlfn.XLOOKUP(A11, '3. orders_clean.csv'!A:A, '3. orders_clean.csv'!F:F)} -> Kalimantan Timur | J11: {=_xlfn.XLOOKUP(B:B, '4. products_clean.csv'!A:A, '4. products_clean.csv'!D:D)} -> Shirt
A12: ORD000007 | B12: PRD013 | C12: 1 | D12: 149000 | E12: {=_xlfn.XLOOKUP(A12, '3. orders_clean.csv'!A:A,'3. orders_clean.csv'!C:C)} -> 44597 | F12: {=_xlfn.XLOOKUP(A12, '3. orders_clean.csv'!A:A, '3. orders_clean.csv'!I:I)} -> delivered | G12: {=_xlfn.XLOOKUP(A12, '3. orders_clean.csv'!A:A, '3. orders_clean.csv'!J:J)} -> FALSE | H12: {=_xlfn.XLOOKUP(A12, '3. orders_clean.csv'!A:A, '3. orders_clean.csv'!E:E)} -> Bekasi | I12: {=_xlfn.XLOOKUP(A12, '3. orders_clean.csv'!A:A, '3. orders_clean.csv'!F:F)} -> Jawa Barat | J12: {=_xlfn.XLOOKUP(B:B, '4. products_clean.csv'!A:A, '4. products_clean.csv'!D:D)} -> Pants
A13: ORD000007 | B13: PRD230 | C13: 2 | D13: 258000 | E13: {=_xlfn.XLOOKUP(A13, '3. orders_clean.csv'!A:A,'3. orders_clean.csv'!C:C)} -> 44597 | F13: {=_xlfn.XLOOKUP(A13, '3. orders_clean.csv'!A:A, '3. orders_clean.csv'!I:I)} -> delivered | G13: {=_xlfn.XLOOKUP(A13, '3. orders_clean.csv'!A:A, '3. orders_clean.csv'!J:J)} -> FALSE | H13: {=_xlfn.XLOOKUP(A13, '3. orders_clean.csv'!A:A, '3. orders_clean.csv'!E:E)} -> Bekasi | I13: {=_xlfn.XLOOKUP(A13, '3. orders_clean.csv'!A:A, '3. orders_clean.csv'!F:F)} -> Jawa Barat | J13: {=_xlfn.XLOOKUP(B:B, '4. products_clean.csv'!A:A, '4. products_clean.csv'!D:D)} -> Accessories
... A4987: ORD003000 | B4987: PRD117 | C4987: 1 | D4987: 49000 | E4987: {=_xlfn.XLOOKUP(A4987, '3. orders_clean.csv'!A:A,'3. orders_clean.csv'!C:C)} -> 45434 | F4987: {=_xlfn.XLOOKUP(A4987, '3. orders_clean.csv'!A:A, '3. orders_clean.csv'!I:I)} -> returned | G4987: {=_xlfn.XLOOKUP(A4987, '3. orders_clean.csv'!A:A, '3. orders_clean.csv'!J:J)} -> TRUE | H4987: {=_xlfn.XLOOKUP(A4987, '3. orders_clean.csv'!A:A, '3. orders_clean.csv'!E:E)} -> Depok | I4987: {=_xlfn.XLOOKUP(A4987, '3. orders_clean.csv'!A:A, '3. orders_clean.csv'!F:F)} -> Jawa Barat | J4987: {=_xlfn.XLOOKUP(B:B, '4. products_clean.csv'!A:A, '4. products_clean.csv'!D:D)} -> Jacket

Sheet 5. reviews.csv
A1: review_id | B1: order_id | C1: product_id | D1: customer_id | E1: rating | F1: review_text | G1: review_date | H1: helpful_count
A2: REV00001 | B2: ORD000131 | C2: PRD269 | D2: CUST0714 | E2: 3 | F2: Bahan premium, jahitan kuat. | G2: 45338 | H2: 0
A3: REV00002 | B3: ORD001162 | C3: PRD105 | D3: CUST0586 | E3: 2 | F3: Bagus banget, packaging juga aman. | G3: 45681 | H3: 0
A4: REV00003 | B4: ORD001172 | C4: PRD053 | D4: CUST0164 | E4: 5 | F4: Modelnya keren, fit di badan. | G4: 45553 | H4: 18
A5: REV00004 | B5: ORD002879 | C5: PRD265 | D5: CUST0179 | E5: 4 | F5: Kualitas oke untuk harga segini. | G5: 45367 | H5: 0
A6: REV00005 | B6: ORD001303 | C6: PRD252 | D6: CUST0606 | E6: 3 | F6: Produk sampai dengan cepat, sesuai ekspektasi. | G6: 45317 | H6: 46
A7: REV00006 | B7: ORD002340 | C7: PRD028 | D7: CUST0465 | E7: 5 | F7: Mantap, langganan terus dari sini. | G7: 45287 | H7: 0
A8: REV00007 | B8: ORD002140 | C8: PRD096 | D8: CUST0616 | E8: 5 | F8: Sesuai deskripsi, akan beli lagi. | G8: 45319 | H8: 0
A9: REV00008 | B9: ORD002124 | C9: PRD023 | D9: CUST0030 | E9: 5 | F9: Wah ini sih murah meriah tapi berkualitas. | G9: 45446 | H9: 11
A10: REV00009 | B10: ORD002964 | C10: PRD181 | D10: CUST0479 | E10: 3 | F10: Produknya bagus tapi pengiriman lama. | G10: 45204 | H10: 0
A11: REV00010 | B11: ORD001442 | C11: PRD072 | D11: CUST0550 | E11: 3 | F11: Modelnya keren, fit di badan. | G11: 45239 | H11: 0
A12: REV00011 | B12: ORD002046 | C12: PRD254 | D12: CUST0488 | E12: 5 | G12: 45460 | H12: 0
A13: REV00012 | B13: ORD001842 | C13: PRD019 | D13: CUST0480 | E13: 4 | F13: Pengiriman cepat, packaging rapi. | G13: 45667 | H13: 6
A14: REV00013 | B14: ORD000293 | C14: PRD150 | D14: CUST0135 | E14: 5 | F14: Suka banget, repeat order pasti. | G14: 44677 | H14: 9
A15: REV00014 | B15: ORD001301 | C15: PRD210 | D15: CUST0141 | E15: 5 | F15: Ukuran agak kekecilan, tapi bahan oke. | G15: 44717 | H15: 11
A16: REV00015 | B16: ORD001293 | C16: PRD270 | D16: CUST0531 | E16: 4 | F16: Pengiriman cepat, packaging rapi. | G16: 44918 | H16: 9
A17: REV00016 | B17: ORD000867 | C17: PRD259 | D17: CUST0270 | E17: 5 | F17: Bagus banget, packaging juga aman. | G17: 45132 | H17: 31
A18: REV00017 | B18: ORD001287 | C18: PRD280 | D18: CUST0048 | E18: 5 | F18: Produk original, terima kasih seller. | G18: 45593 | H18: 0
A19: REV00018 | B19: ORD000965 | C19: PRD102 | D19: CUST0758 | E19: 3 | F19: Jahitannya kurang rapi, tapi masih bisa dipake. | G19: 45595 | H19: 6
A20: REV00019 | B20: ORD000890 | C20: PRD195 | D20: CUST0778 | E20: 5 | F20: Awalnya ragu, ternyata kualitasnya oke. | G20: 45401 | H20: 0
A21: REV00020 | B21: ORD002400 | C21: PRD172 | D21: CUST0417 | E21: 5 | F21: Agak mengecewakan, bahannya panas. | G21: 45210 | H21: 0
A22: REV00021 | B22: ORD002369 | C22: PRD196 | D22: CUST0259 | E22: 5 | F22: Suka banget, repeat order pasti. | G22: 45522 | H22: 3
A23: REV00022 | B23: ORD001470 | C23: PRD297 | D23: CUST0376 | E23: 5 | F23: Warna agak beda dari foto. | G23: 44927 | H23: 0
A24: REV00023 | B24: ORD002158 | C24: PRD213 | D24: CUST0682 | E24: 4 | G24: 45157 | H24: 10
A25: REV00024 | B25: ORD000417 | C25: PRD013 | D25: CUST0527 | E25: 4 | F25: Produk sampai dengan cepat, sesuai ekspektasi. | G25: 45363 | H25: 4
A26: REV00025 | B26: ORD002694 | C26: PRD298 | D26: CUST0293 | E26: 5 | F26: Tidak sesuai ekspektasi, kurang puas. | G26: 45103 | H26: 0
A27: REV00026 | B27: ORD001044 | C27: PRD181 | D27: CUST0226 | E27: 5 | F27: Cocok buat hangout, modelnya kekinian. | G27: 45272 | H27: 10
A28: REV00027 | B28: ORD000043 | C28: PRD009 | D28: CUST0575 | E28: 4 | G28: 45388 | H28: 2
A29: REV00028 | B29: ORD002050 | C29: PRD005 | D29: CUST0521 | E29: 3 | F29: Bahannya enak banget, jahitan rapi. Recommended! | G29: 45675 | H29: 0
A30: REV00029 | B30: ORD000334 | C30: PRD001 | D30: CUST0148 | E30: 5 | F30: Kainnya tipis, agak kecewa. | G30: 44637 | H30: 0
A31: REV00030 | B31: ORD002146 | C31: PRD026 | D31: CUST0354 | E31: 5 | F31: Modelnya simple, gampang di-mix and match. | G31: 44905 | H31: 0
A32: REV00031 | B32: ORD001633 | C32: PRD156 | D32: CUST0573 | E32: 5 | F32: Warna agak beda dari foto. | G32: 45396 | H32: 9
A33: REV00032 | B33: ORD001736 | C33: PRD219 | D33: CUST0160 | E33: 5 | F33: Bahan premium, jahitan kuat. | G33: 44922 | H33: 10
A34: REV00033 | B34: ORD000016 | C34: PRD052 | D34: CUST0441 | E34: 4 | F34: Bagus banget, packaging juga aman. | G34: 45424 | H34: 3
A35: REV00034 | B35: ORD000216 | C35: PRD060 | D35: CUST0177 | E35: 5 | F35: Awalnya ragu, ternyata kualitasnya oke. | G35: 45566 | H35: 0
A36: REV00035 | B36: ORD002501 | C36: PRD113 | D36: CUST0565 | E36: 3 | F36: Kualitas oke untuk harga segini. | G36: 44677 | H36: 0
A37: REV00036 | B37: ORD002750 | C37: PRD298 | D37: CUST0096 | E37: 4 | F37: Bagus banget, packaging juga aman. | G37: 45418 | H37: 6
A38: REV00037 | B38: ORD001607 | C38: PRD275 | D38: CUST0143 | E38: 5 | F38: Bahannya enak banget, jahitan rapi. Recommended! | G38: 44647 | H38: 27
A39: REV00038 | B39: ORD000825 | C39: PRD276 | D39: CUST0218 | E39: 3 | F39: Produk original, terima kasih seller. | G39: 45720 | H39: 0
A40: REV00039 | B40: ORD001079 | C40: PRD195 | D40: CUST0057 | E40: 5 | F40: Bahan premium, jahitan kuat. | G40: 45053 | H40: 0
... A46: REV00045 | B46: ORD002284 | C46: PRD289 | D46: CUST0352 | E46: 4 | F46: Jahitannya kurang rapi, tapi masih bisa dipake. | G46: 45697 | H46: 0
A47: REV00046 | B47: ORD001408 | C47: PRD016 | D47: CUST0219 | E47: 1 | G47: 45404 | H47: 23
A48: REV00047 | B48: ORD001656 | C48: PRD286 | D48: CUST0070 | E48: 2 | F48: Cocok buat hangout, modelnya kekinian. | G48: 45181 | H48: 10
A49: REV00048 | B49: ORD002406 | C49: PRD002 | D49: CUST0712 | E49: 2 | G49: 45595 | H49: 26
A50: REV00049 | B50: ORD002343 | C50: PRD140 | D50: CUST0159 | E50: 5 | G50: 44988 | H50: 0
A51: REV00050 | B51: ORD000055 | C51: PRD212 | D51: CUST0442 | E51: 4 | F51: Awalnya ragu, ternyata kualitasnya oke. | G51: 45684 | H51: 0
A52: REV00051 | B52: ORD002426 | C52: PRD131 | D52: CUST0636 | E52: 5 | F52: Produknya bagus tapi pengiriman lama. | G52: 45182 | H52: 3
A53: REV00052 | B53: ORD002260 | C53: PRD022 | D53: CUST0462 | E53: 3 | F53: Bahan adem, cocok buat sehari-hari. | G53: 45212 | H53: 39
A54: REV00053 | B54: ORD001328 | C54: PRD261 | D54: CUST0740 | E54: 5 | F54: Pelayanan seller ramah, fast response. | G54: 45616 | H54: 0
A55: REV00054 | B55: ORD000409 | C55: PRD289 | D55: CUST0557 | E55: 5 | F55: Agak mengecewakan, bahannya panas. | G55: 45304 | H55: 0
A56: REV00055 | B56: ORD001918 | C56: PRD205 | D56: CUST0503 | E56: 5 | F56: Ukuran pas di badan, warna sesuai foto. | G56: 45354 | H56: 0
A57: REV00056 | B57: ORD002897 | C57: PRD090 | D57: CUST0280 | E57: 4 | F57: Cocok buat hangout, modelnya kekinian. | G57: 45571 | H57: 0
A58: REV00057 | B58: ORD001929 | C58: PRD039 | D58: CUST0636 | E58: 5 | F58: Bahan adem, cocok buat sehari-hari. | G58: 45296 | H58: 0
A59: REV00058 | B59: ORD000072 | C59: PRD209 | D59: CUST0379 | E59: 5 | F59: Kualitas oke untuk harga segini. | G59: 45457 | H59: 5
A60: REV00059 | B60: ORD001919 | C60: PRD019 | D60: CUST0153 | E60: 3 | F60: Kainnya tipis, agak kecewa. | G60: 45510 | H60: 15
A61: REV00060 | B61: ORD001673 | C61: PRD259 | D61: CUST0373 | E61: 2 | F61: Modelnya keren, fit di badan. | G61: 45464 | H61: 0
A62: REV00061 | B62: ORD000676 | C62: PRD093 | D62: CUST0680 | E62: 2 | F62: Mantap, langganan terus dari sini. | G62: 44714 | H62: 2
A63: REV00062 | B63: ORD001231 | C63: PRD024 | D63: CUST0605 | E63: 4 | F63: Mantap, langganan terus dari sini. | G63: 45215 | H63: 0
A64: REV00063 | B64: ORD002331 | C64: PRD058 | D64: CUST0288 | E64: 3 | G64: 44947 | H64: 8
A65: REV00064 | B65: ORD002956 | C65: PRD084 | D65: CUST0057 | E65: 5 | F65: Bahan premium, jahitan kuat. | G65: 45534 | H65: 16
A66: REV00065 | B66: ORD002177 | C66: PRD291 | D66: CUST0540 | E66: 5 | F66: Pengiriman cepat, packaging rapi. | G66: 45683 | H66: 0
A67: REV00066 | B67: ORD002587 | C67: PRD008 | D67: CUST0193 | E67: 4 | F67: Pengiriman ngaret tapi barang bagus. | G67: 45186 | H67: 19
A68: REV00067 | B68: ORD002188 | C68: PRD153 | D68: CUST0015 | E68: 4 | F68: Worth it dengan harganya. | G68: 44581 | H68: 3
A69: REV00068 | B69: ORD000625 | C69: PRD127 | D69: CUST0233 | E69: 3 | F69: Pengiriman ngaret tapi barang bagus. | G69: 45058 | H69: 0
A70: REV00069 | B70: ORD001708 | C70: PRD070 | D70: CUST0269 | E70: 4 | F70: Cocok buat hangout, modelnya kekinian. | G70: 44998 | H70: 5
A71: REV00070 | B71: ORD000265 | C71: PRD258 | D71: CUST0735 | E71: 4 | F71: Untuk harga segini, kualitasnya mantap. | G71: 45107 | H71: 3
A72: REV00071 | B72: ORD002997 | C72: PRD228 | D72: CUST0327 | E72: 5 | F72: Worth it dengan harganya. | G72: 45351 | H72: 23
A73: REV00072 | B73: ORD001584 | C73: PRD295 | D73: CUST0772 | E73: 3 | F73: Modelnya simple, gampang di-mix and match. | G73: 45595 | H73: 7
A74: REV00073 | B74: ORD000297 | C74: PRD188 | D74: CUST0794 | E74: 4 | F74: Bagus banget, suka sama designnya. | G74: 45134 | H74: 0
A75: REV00074 | B75: ORD000593 | C75: PRD260 | D75: CUST0145 | E75: 5 | F75: Agak mengecewakan, bahannya panas. | G75: 45129 | H75: 20
A76: REV00075 | B76: ORD002255 | C76: PRD036 | D76: CUST0709 | E76: 4 | F76: Kualitas oke untuk harga segini. | G76: 45088 | H76: 3
A77: REV00076 | B77: ORD001867 | C77: PRD077 | D77: CUST0281 | E77: 4 | F77: Awalnya ragu, ternyata kualitasnya oke. | G77: 45525 | H77: 0
A78: REV00077 | B78: ORD001577 | C78: PRD296 | D78: CUST0001 | E78: 4 | G78: 45321 | H78: 0
A79: REV00078 | B79: ORD002939 | C79: PRD234 | D79: CUST0301 | E79: 5 | F79: Jahitannya kurang rapi, tapi masih bisa dipake. | G79: 44950 | H79: 0
A80: REV00079 | B80: ORD000899 | C80: PRD199 | D80: CUST0531 | E80: 4 | F80: Kainnya tipis, agak kecewa. | G80: 45542 | H80: 0
A81: REV00080 | B81: ORD000269 | C81: PRD202 | D81: CUST0122 | E81: 4 | F81: Bagus banget, packaging juga aman. | G81: 44945 | H81: 0
A82: REV00081 | B82: ORD002959 | C82: PRD163 | D82: CUST0179 | E82: 3 | F82: Untuk harga segini, kualitasnya mantap. | G82: 44972 | H82: 0
A83: REV00082 | B83: ORD000640 | C83: PRD271 | D83: CUST0297 | E83: 4 | F83: Produk sampai dengan cepat, sesuai ekspektasi. | G83: 44723 | H83: 5
A84: REV00083 | B84: ORD002252 | C84: PRD204 | D84: CUST0221 | E84: 5 | F84: Agak mengecewakan, bahannya panas. | G84: 45677 | H84: 7
A85: REV00084 | B85: ORD002592 | C85: PRD114 | D85: CUST0182 | E85: 5 | F85: Cocok buat hangout, modelnya kekinian. | G85: 45118 | H85: 5
A86: REV00085 | B86: ORD001682 | C86: PRD267 | D86: CUST0505 | E86: 4 | F86: Produknya bagus tapi pengiriman lama. | G86: 45009 | H86: 15
A87: REV00086 | B87: ORD001610 | C87: PRD256 | D87: CUST0527 | E87: 2 | F87: Kualitas oke untuk harga segini. | G87: 45391 | H87: 7
A88: REV00087 | B88: ORD001256 | C88: PRD222 | D88: CUST0264 | E88: 5 | F88: Bagus banget, suka sama designnya. | G88: 45456 | H88: 15
A89: REV00088 | B89: ORD002500 | C89: PRD080 | D89: CUST0291 | E89: 4 | F89: Produknya bagus tapi pengiriman lama. | G89: 45403 | H89: 21
A90: REV00089 | B90: ORD002686 | C90: PRD039 | D90: CUST0576 | E90: 5 | F90: Pelayanan seller ramah, fast response. | G90: 45162 | H90: 2
... A95: REV00094 | B95: ORD002588 | C95: PRD168 | D95: CUST0105 | E95: 4 | F95: Agak mengecewakan, bahannya panas. | G95: 45443 | H95: 49
A96: REV00095 | B96: ORD002074 | C96: PRD040 | D96: CUST0577 | E96: 5 | G96: 45424 | H96: 9
A97: REV00096 | B97: ORD001829 | C97: PRD275 | D97: CUST0024 | E97: 4 | F97: Untuk harga segini, kualitasnya mantap. | G97: 45119 | H97: 22
A98: REV00097 | B98: ORD000432 | C98: PRD066 | D98: CUST0408 | E98: 5 | F98: Pelayanan seller ramah, fast response. | G98: 44567 | H98: 24
A99: REV00098 | B99: ORD000245 | C99: PRD227 | D99: CUST0356 | E99: 3 | F99: Ukuran sesuai size chart, recommended. | G99: 45711 | H99: 0
A100: REV00099 | B100: ORD000798 | C100: PRD064 | D100: CUST0052 | E100: 5 | F100: Wah ini sih murah meriah tapi berkualitas. | G100: 45245 | H100: 5
A101: REV00100 | B101: ORD002808 | C101: PRD221 | D101: CUST0295 | E101: 3 | F101: Worth it dengan harganya. | G101: 44909 | H101: 7
A102: REV00101 | B102: ORD001855 | C102: PRD184 | D102: CUST0749 | E102: 3 | F102: Untuk harga segini, kualitasnya mantap. | G102: 45161 | H102: 19
A103: REV00102 | B103: ORD000609 | C103: PRD220 | D103: CUST0515 | E103: 5 | F103: Produk original, terima kasih seller. | G103: 45671 | H103: 0
A104: REV00103 | B104: ORD001041 | C104: PRD187 | D104: CUST0241 | E104: 5 | F104: Pengiriman ngaret tapi barang bagus. | G104: 45078 | H104: 0
A105: REV00104 | B105: ORD002683 | C105: PRD039 | D105: CUST0104 | E105: 5 | F105: Cocok buat hangout, modelnya kekinian. | G105: 45236 | H105: 8
A106: REV00105 | B106: ORD001139 | C106: PRD281 | D106: CUST0431 | E106: 5 | F106: Ukuran pas di badan, warna sesuai foto. | G106: 45416 | H106: 0
A107: REV00106 | B107: ORD001538 | C107: PRD271 | D107: CUST0050 | E107: 5 | F107: Wah ini sih murah meriah tapi berkualitas. | G107: 45691 | H107: 0
A108: REV00107 | B108: ORD000594 | C108: PRD004 | D108: CUST0409 | E108: 5 | F108: Pelayanan seller ramah, fast response. | G108: 45110 | H108: 10
... A117: REV00116 | B117: ORD000765 | C117: PRD101 | D117: CUST0411 | E117: 4 | F117: Untuk harga segini, kualitasnya mantap. | G117: 45297 | H117: 8
...

Sheet 5. reviews_clean.csv
A1: review_id | B1: order_id | C1: product_id | D1: customer_id | E1: rating | F1: review_text | G1: review_date | H1: helpful_count
A2: REV00001 | B2: ORD000131 | C2: PRD269 | D2: CUST0714 | E2: 3 | F2: Bahan premium, jahitan kuat. | G2: 45338 | H2: 0
A3: REV00002 | B3: ORD001162 | C3: PRD105 | D3: CUST0586 | E3: 2 | F3: Bagus banget, packaging juga aman. | G3: 45681 | H3: 0
A4: REV00003 | B4: ORD001172 | C4: PRD053 | D4: CUST0164 | E4: 5 | F4: Modelnya keren, fit di badan. | G4: 45553 | H4: 18
A5: REV00004 | B5: ORD002879 | C5: PRD265 | D5: CUST0179 | E5: 4 | F5: Kualitas oke untuk harga segini. | G5: 45367 | H5: 0
A6: REV00005 | B6: ORD001303 | C6: PRD252 | D6: CUST0606 | E6: 3 | F6: Produk sampai dengan cepat, sesuai ekspektasi. | G6: 45317 | H6: 46
A7: REV00006 | B7: ORD002340 | C7: PRD028 | D7: CUST0465 | E7: 5 | F7: Mantap, langganan terus dari sini. | G7: 45287 | H7: 0
A8: REV00007 | B8: ORD002140 | C8: PRD096 | D8: CUST0616 | E8: 5 | F8: Sesuai deskripsi, akan beli lagi. | G8: 45319 | H8: 0
A9: REV00008 | B9: ORD002124 | C9: PRD023 | D9: CUST0030 | E9: 5 | F9: Wah ini sih murah meriah tapi berkualitas. | G9: 45446 | H9: 11
A10: REV00009 | B10: ORD002964 | C10: PRD181 | D10: CUST0479 | E10: 3 | F10: Produknya bagus tapi pengiriman lama. | G10: 45204 | H10: 0
A11: REV00010 | B11: ORD001442 | C11: PRD072 | D11: CUST0550 | E11: 3 | F11: Modelnya keren, fit di badan. | G11: 45239 | H11: 0
A12: REV00011 | B12: ORD002046 | C12: PRD254 | D12: CUST0488 | E12: 5 | F12: Kosong | G12: 45460 | H12: 0
A13: REV00012 | B13: ORD001842 | C13: PRD019 | D13: CUST0480 | E13: 4 | F13: Pengiriman cepat, packaging rapi. | G13: 45667 | H13: 6
... A1501: REV01500 | B1501: ORD002062 | C1501: PRD185 | D1501: CUST0076 | E1501: 4 | F1501: Untuk harga segini, kualitasnya mantap. | G1501: 45451 | H1501: 18

Sheet definisi revenue loss
A1: Definisi Revenue Loss = total nilai order yang cancelled + returned (328 + 151 order dari 3000).

Sheet mapping_kategori
A1: kategori_lama | B1: kategori_baru
A2: {=UNIQUE('4. products_clean.csv'!C:C)} -> category | B2: Kategori
A3: dress | B3: Dress
A4: T-Shirt | B4: T-Shirt
A5: Accessories | B5: Accessories
A6: Pants | B6: Pants
A7: Kaos | B7: T-Shirt
A8: Jaket | B8: Jacket
A9: kaos | B9: T-Shirt
A10: Aksesoris | B10: Accessories
A11: Shirt | B11: Shirt
A12: Celana | B12: Pants
A13: Jacket | B13: Jacket
A14: Dress | B14: Dress
... A16: Kemeja | B16: Shirt
